<?xml version="1.0" encoding="UTF-8"?>
<QW value="天津市南开区人民法院&#xD;&#xA;民   事   判   决   书&#xD;&#xA;（2008）南民初字第911号&#xD;&#xA;原告张守锁,男,汉族,1945年10月30日出生,公安南开分局退休干部,住天津市南开区黄河道新华楼5-1-5，身份证号：120104194510302110。&#xD;&#xA;被告高洪芝,女,1949年9月24日出生，汉族，天津市彩色电视胶制品六厂退休职工，住同原告，身份证号：120104194909242121。&#xD;&#xA;原告张守锁与被告高洪芝离婚纠纷一案，本院受理后，依法由助理审判员赵春玲独任审判，公开开庭进行了审理。原告张守锁，被告高洪芝到庭参加诉讼。本案现已审理终结。&#xD;&#xA;原告诉称，婚后双方感情一般，双方在共同生活期间没有共同语言，且性格不合，被告稍有不顺对原告非打即骂,由于被告脾气爆躁，经常为一些生活琐事与原告大吵大闹，致使夫妻感情破裂，现夫妻关系名存实亡，故起诉要求离婚。&#xD;&#xA;被告辩称，原告所述不实,婚后初期被告脾气确实不好,在被告怀孕时由于被原告殴打使婚生子肢体残疾,此后又由于种种原因使其大脑受到刺激，双方一旦离婚残疾儿子无人照管，现在原、被告生活比较正常,原告提出离婚是更年期的表现,因此诚请法院为双方调解合好，故不同意原告离婚之请求。&#xD;&#xA;经审理查明，原、被告于1970年经人介绍相识并确立恋爱关系，同年5月16日登记结婚，1972年2月生育长女张静，现已结婚，1974年生育一子张颂,现肢体残疾。婚后双方感情尚可，近年来，双方因家庭生活琐事等问题确曾产生矛盾。2006年7月3日原告曾起诉要求与被告离婚,后经本院驳回其诉请。现其再次以夫妻感情破裂要求与被告离婚。经询，被告表示虽双方有分歧但夫妻感情并未破裂，双方仍在一起生活，且考虑到离婚后残疾儿子无人照管，因此,不同意离婚，案经调解未果。&#xD;&#xA;本院认为，原、被告系自主结婚，婚后双方共同生活30多年，且夫妻感情尚可。现虽因生活琐事等问题存有分歧，曾出现矛盾，但双方均应正确对待，所产生矛盾被告表示因有一残疾儿子,无人照管，并愿在今后的生活中主动与原告沟通交流，为此，原告应念以往夫妻之情及子女特殊情况，正确处理好家庭矛盾，共同建立和睦文明的家庭。对此，原告再坚持离婚不妥。综上，本院依据《中华人民共和国婚姻法》第三十二条的规定，判决如下：&#xD;&#xA;驳回原告张守锁离婚之请求。&#xD;&#xA;案件受理费200元，减半收取，由原告负担。&#xD;&#xA;如不服本判决，可在判决书送达之日起十五日内，向本院递交上诉状，并按对方当事人的人数提出副本，上诉于天津市第一中级人民法院。&#xD;&#xA;                                             代理审判员  赵春玲&#xD;&#xA;二○○八年  月   日&#xD;&#xA;                                 书  记  员  魏俊刚&#xD;&#xA;1&#xD;&#xA;2&#xD;" nameCN="全文">
  <WS value="天津市南开区人民法院 民事判决书 （2008）南民初字第911号" nameCN="文首">
    <WSZZDW value="法院" nameCN="文书制作单位" />
    <JBFY value="天津市南开区人民法院" nameCN="经办法院">
      <FYJB value="基层" nameCN="法院级别" />
      <XZQH_P value="天津" nameCN="行政区划(省)" />
    </JBFY>
    <WSMC value="民事判决书" nameCN="文书名称" />
    <AH value="（2008）南民初字第911号" nameCN="案号" />
    <LAND value="2008" nameCN="立案年度" />
    <AJXZ value="民事案件" nameCN="案件性质" />
    <WSZL value="判决书" nameCN="文书种类" />
    <SPCX value="一审案件" nameCN="审判程序" />
    <AJLX value="民事一审案件" nameCN="案件类型" />
  </WS>
  <SSCYRQJ value="原告张守锁,男,汉族,1945年10月30日出生,公安南开分局退休干部,住天津市南开区黄河道新华楼5-1-5，身份证号：120104194510302110。 被告高洪芝,女,1949年9月24日出生，汉族，天津市彩色电视胶制品六厂退休职工，住同原告，身份证号：120104194909242121。" nameCN="诉讼参与人全集">
    <SSCYR value="原告张守锁,男,汉族,1945年10月30日出生,公安南开分局退休干部,住天津市南开区黄河道新华楼5-1-5，身份证号：120104194510302110。" nameCN="诉讼参与人">
      <SSCYRMC value="张守锁,男,汉族,1945年10月30日出生,公安南开分局退休干部,住天津市南开区黄河道新华楼5-1-5" nameCN="诉讼参与人名称" />
      <SSSF value="原告" nameCN="诉讼身份" />
      <SSDW value="原告" nameCN="诉讼地位" />
      <DSRLB value="原告" nameCN="当事人类别" />
      <DSRLX value="法人" nameCN="当事人类型" />
      <DSRSFZH value="否" nameCN="当事人是否再婚" />
      <TSHY value="公安" nameCN="特殊行业" />
    </SSCYR>
    <SSCYR value="被告高洪芝,女,1949年9月24日出生，汉族，天津市彩色电视胶制品六厂退休职工，住同原告，身份证号：120104194909242121。" nameCN="诉讼参与人">
      <SSCYRMC value="高洪芝,女,1949年9月24日出生" nameCN="诉讼参与人名称" />
      <SSSF value="被告" nameCN="诉讼身份" />
      <SSDW value="被告" nameCN="诉讼地位" />
      <DSRLB value="被告" nameCN="当事人类别" />
      <DSRLX value="法人" nameCN="当事人类型" />
      <MZ value="汉族" nameCN="民族" />
      <DSRDZ value="同原告" nameCN="当事人地址" />
      <DWZWFZ nameCN="单位职务分组">
        <ZW value="退休职工" nameCN="职务" />
      </DWZWFZ>
      <DSRSFZH value="否" nameCN="当事人是否再婚" />
    </SSCYR>
    <SSCYRQJ value="错误" nameCN="保险公司是否作为被告" />
  </SSCYRQJ>
  <SSJL value="原告张守锁与被告高洪芝离婚纠纷一案，本院受理后，依法由助理审判员赵春玲独任审判，公开开庭进行了审理。原告张守锁，被告高洪芝到庭参加诉讼。本案现已审理终结。" nameCN="诉讼记录">
    <AY value="离婚纠纷" nameCN="案由" />
    <KTSL value="是" nameCN="开庭审理" />
    <KTSLXX value="公开审理" nameCN="开庭审理信息" />
    <WZAY value="离婚纠纷" nameCN="完整案由" />
    <AYDM value="9015" nameCN="案由代码" />
    <YSAJSYCX value="普通程序" nameCN="一审案件适用程序" />
    <JYZPT value="否" nameCN="简易转普通" />
    <YSAJLY value="新收" nameCN="一审案件来源" />
  </SSJL>
  <AJJBQK value="原告诉称，婚后双方感情一般，双方在共同生活期间没有共同语言，且性格不合，被告稍有不顺对原告非打即骂,由于被告脾气爆躁，经常为一些生活琐事与原告大吵大闹，致使夫妻感情破裂，现夫妻关系名存实亡，故起诉要求离婚。 被告辩称，原告所述不实,婚后初期被告脾气确实不好,在被告怀孕时由于被原告殴打使婚生子肢体残疾,此后又由于种种原因使其大脑受到刺激，双方一旦离婚残疾儿子无人照管，现在原、被告生活比较正常,原告提出离婚是更年期的表现,因此诚请法院为双方调解合好，故不同意原告离婚之请求。 经审理查明，原、被告于1970年经人介绍相识并确立恋爱关系，同年5月16日登记结婚，1972年2月生育长女张静，现已结婚，1974年生育一子张颂,现肢体残疾。婚后双方感情尚可，近年来，双方因家庭生活琐事等问题确曾产生矛盾。2006年7月3日原告曾起诉要求与被告离婚,后经本院驳回其诉请。现其再次以夫妻感情破裂要求与被告离婚。经询，被告表示虽双方有分歧但夫妻感情并未破裂，双方仍在一起生活，且考虑到离婚后残疾儿子无人照管，因此,不同意离婚，案经调解未果。" nameCN="案件基本情况">
    <YGSCD value="原告诉称，婚后双方感情一般，双方在共同生活期间没有共同语言，且性格不合，被告稍有不顺对原告非打即骂,由于被告脾气爆躁，经常为一些生活琐事与原告大吵大闹，致使夫妻感情破裂，现夫妻关系名存实亡，故起诉要求离婚。 " nameCN="原告诉称段" />
    <SGXQ value="未提及" nameCN="事故详情">
      <SGSJ value="未提及" nameCN="事故时间" />
      <SGDD value="未提及" nameCN="事故地点" />
    </SGXQ>
    <JDCSYR value="高洪芝,女,1949年9月24日出生" nameCN="机动车所有人" />
    <BGBCD value="被告辩称，原告所述不实,婚后初期被告脾气确实不好,在被告怀孕时由于被原告殴打使婚生子肢体残疾,此后又由于种种原因使其大脑受到刺激，双方一旦离婚残疾儿子无人照管，现在原、被告生活比较正常,原告提出离婚是更年期的表现,因此诚请法院为双方调解合好，故不同意原告离婚之请求。 " nameCN="被告辩称段" />
    <CMSSD value="经审理查明，原、被告于1970年经人介绍相识并确立恋爱关系，同年5月16日登记结婚，1972年2月生育长女张静，现已结婚，1974年生育一子张颂,现肢体残疾。婚后双方感情尚可，近年来，双方因家庭生活琐事等问题确曾产生矛盾。2006年7月3日原告曾起诉要求与被告离婚,后经本院驳回其诉请。现其再次以夫妻感情破裂要求与被告离婚。经询，被告表示虽双方有分歧但夫妻感情并未破裂，双方仍在一起生活，且考虑到离婚后残疾儿子无人照管，因此,不同意离婚，案经调解未果。" nameCN="查明事实段" />
  </AJJBQK>
  <CPFXGC value="本院认为，原、被告系自主结婚，婚后双方共同生活30多年，且夫妻感情尚可。现虽因生活琐事等问题存有分歧，曾出现矛盾，但双方均应正确对待，所产生矛盾被告表示因有一残疾儿子,无人照管，并愿在今后的生活中主动与原告沟通交流，为此，原告应念以往夫妻之情及子女特殊情况，正确处理好家庭矛盾，共同建立和睦文明的家庭。对此，原告再坚持离婚不妥。综上，本院依据《中华人民共和国婚姻法》第三十二条的规定，判决如下：" nameCN="裁判分析过程">
    <JAFSLX value="判决" nameCN="结案方式类型" />
    <FLFTMC value="中华人民共和国婚姻法" nameCN="法律法条名称">
      <TM value="三十二" nameCN="条目" />
    </FLFTMC>
  </CPFXGC>
  <CPJG value="驳回原告张守锁离婚之请求。 案件受理费200元，减半收取，由原告负担。 如不服本判决，可在判决书送达之日起十五日内，向本院递交上诉状，并按对方当事人的人数提出副本，上诉于天津市第一中级人民法院。" nameCN="裁判结果">
    <JAFS value="判决" nameCN="结案方式" />
    <PCSFSXZQ value="正确" nameCN="同时起诉侵权人与保险公司的赔偿顺序" />
    <JTPJJG value="驳回原告张守锁离婚之请求。" nameCN="具体裁判段" />
    <SSFCD nameCN="诉讼费承担">
      <SSFCDJL value="案件受理费200元，减半收取，由原告负担。" nameCN="诉讼费承担记录">
        <SSFJE value="200元" nameCN="诉讼费金额" />
        <SSFZL value="受理费" nameCN="诉讼费种类" />
      </SSFCDJL>
    </SSFCD>
    <SFFHCS value="否" nameCN="是否发回重审" />
    <KSSZ value="天津市第一中级人民法院" nameCN="可上诉至" />
    <SSTJCL value="上诉状，并按对方当事人的人数提出副本" nameCN="上诉提交材料" />
    <SSQX value="十五日" nameCN="上诉期限" />
    <TCGXQYY value="否" nameCN="是否提出管辖权异议" />
  </CPJG>
  <WW value="代理审判员赵春玲 二○○八年月日 书记员魏俊刚 1 2 " nameCN="文尾">
    <SPZZCY nameCN="审判组织成员">
      <SPRYXM value="魏俊刚" nameCN="审判人员姓名" />
      <SPRYJS value="书记员" nameCN="审判人员角色" />
    </SPZZCY>
    <SPZZCY nameCN="审判组织成员">
      <SPRYXM value="赵春玲" nameCN="审判人员姓名" />
      <SPRYJS value="代理审判员" nameCN="审判人员角色" />
    </SPZZCY>
  </WW>
</QW>

