<?xml version="1.0" encoding="UTF-8"?>
<QW value="天津市河西区人民法院&#xD;&#xA;民 事 判 决 书&#xD;&#xA;（2007）西民二初字第517号&#xD;&#xA;原告曹玉慧，女，1953年2月1日出生，汉族，天津市建筑设计院退休职工，住天津市河西区围堤道健强里17门407室。&#xD;&#xA;法定代理人刘婧，女，1985年1月16日出生，汉族，河北省北华航天工业学院学生，住同原告。&#xD;&#xA;被告刘连发，男，1953年4月29日出生，汉族，天津市建筑公司第二分公司工人，住同原告。&#xD;&#xA;原告曹玉慧与被告刘连发离婚纠纷一案，本院于2007年4月16日立案受理后，依法由代理审判员王承铭适用简易程序，公开开庭进行了审理。原告曹玉慧、被告刘连发均到庭参加了诉讼，本案现已审理终结。&#xD;&#xA;原告曹玉慧诉称，我与被告婚后经常因琐事发生矛盾。被告对我进行殴打，给我及子女造成严重伤害。我曾于2006年6月起诉离婚，被判决驳回。后双方仍无法共同生活，夫妻感情已彻底破裂，故起诉要求与被告离婚。&#xD;&#xA;被告辩称，我与原告婚后虽因琐事闹矛盾，我确实也曾动手打过原告，但单亲家庭对孩子影响不好，故我不同意离   婚。如果孩子能够接受，我就同意离婚。&#xD;&#xA;经审理查明，原、被告于1982年经人介绍相识恋爱。1983年1月14日登记结婚，1985年1月16日生一女名刘婧。双方婚前及婚后初期感情尚可，后因生活琐事双方发生矛盾，致使之间产生隔阂。原告曾于2006年6月诉至本院，要求与被告离婚。经判决驳回。双方仍未和好，故原告再次以夫妻感情破裂为由诉至本院，要求与被告离婚。&#xD;&#xA;另查，原、被告无婚前财产、婚后共同财产为海尔空调一台、西门子电冰箱一台、4组组合家具一套、写字台一件、双人床一张、单人床一张、抽油烟机架子一个、书架一个。双方现居住原告名下坐落在天津市河西区健强里17门407-413室公产房屋一套。&#xD;&#xA;上述事实有原、被告当庭陈述、公有住房租赁合同、（2006）西民二初字第178号民事判决书为证，本院予以确认。&#xD;&#xA;本院认为，原、被告虽系自由恋爱、自主结婚，但婚后不注重夫妻感情的培养，经常因琐事发生矛盾，并有被告殴打原告现象的发生。如再勉强维系，对双方均无益。故对原告要求与被告离婚的诉讼请求，本院予以支持。关于财产，本院依法分割。关于住房，因双方均不能出资安置对方，应分室居住为宜。关于原告要求被告给付子女学费的诉讼请求，因其子女已独立生活，故本院不予支持。另对原告要求被告赔偿的诉讼请求，不符合法律规定，故不予支持。综上依据《中华人民共和国婚姻法》第三十二条第二款、第三十九条第一款之规定，判决如下：&#xD;&#xA;一、准予原告曹玉慧与被告刘连发离婚。&#xD;&#xA;二、坐落在天津市河西区围堤道健强里17门407-413室公产房屋一套，408室房屋（大间）由原告曹玉慧租住、407室房屋（小间）由被告刘连发租住。&#xD;&#xA;三、婚后共同财产海尔空调一台、西门子电冰箱一台、4组组合家具一套、单人床一张、归原告所有。书架一个、写字台一件、双人床一张、抽油烟机架子一个归被告刘连发所有。&#xD;&#xA;四、驳回原告曹玉慧要求被告刘连发赔偿的诉讼请求。&#xD;&#xA;五、驳回原告曹玉慧要求被告刘连发支付子女学费的诉讼请求。&#xD;&#xA;案件受理费200元减半收取，由原告曹玉慧负担50元，被告刘连发负担50元（此款于本判决生效之日起5日内履行）。&#xD;&#xA;如不服本判决，可在判决书送达之日起十五日内向本院提出上诉，并按对方当事人的人数提出副本，上诉于天津市第二中级人民法院。&#xD;&#xA;代理审判员  王承铭&#xD;&#xA;二零零七年  月   日&#xD;&#xA;书  记  员  陈爱迪&#xD;" nameCN="全文">
  <WS value="天津市河西区人民法院 民事判决书 （2007）西民二初字第517号" nameCN="文首">
    <WSZZDW value="法院" nameCN="文书制作单位" />
    <JBFY value="天津市河西区人民法院" nameCN="经办法院">
      <FYJB value="基层" nameCN="法院级别" />
      <XZQH_P value="天津" nameCN="行政区划(省)" />
    </JBFY>
    <WSMC value="民事判决书" nameCN="文书名称" />
    <AH value="（2007）西民二初字第517号" nameCN="案号" />
    <LAND value="2007" nameCN="立案年度" />
    <AJXZ value="民事案件" nameCN="案件性质" />
    <WSZL value="判决书" nameCN="文书种类" />
    <SPCX value="一审案件" nameCN="审判程序" />
    <AJLX value="民事一审案件" nameCN="案件类型" />
  </WS>
  <SSCYRQJ value="原告曹玉慧，女，1953年2月1日出生，汉族，天津市建筑设计院退休职工，住天津市河西区围堤道健强里17门407室。 法定代理人刘婧，女，1985年1月16日出生，汉族，河北省北华航天工业学院学生，住同原告。 被告刘连发，男，1953年4月29日出生，汉族，天津市建筑公司第二分公司工人，住同原告。" nameCN="诉讼参与人全集">
    <SSCYR value="原告曹玉慧，女，1953年2月1日出生，汉族，天津市建筑设计院退休职工，住天津市河西区围堤道健强里17门407室。" nameCN="诉讼参与人">
      <SSCYRMC value="曹玉慧" nameCN="诉讼参与人名称" />
      <SSSF value="原告" nameCN="诉讼身份" />
      <SSDW value="原告" nameCN="诉讼地位" />
      <DSRLB value="原告" nameCN="当事人类别" />
      <DSRLX value="自然人" nameCN="当事人类型" />
      <XB value="女" nameCN="性别" />
      <MZ value="汉族" nameCN="民族" />
      <CSRQ value="1953年2月1日" nameCN="出生日期">
        <Year value="1953" nameCN="年" />
        <Month value="2" nameCN="月" />
        <Day value="1" nameCN="日" />
      </CSRQ>
      <GJ value="中国" nameCN="国籍" />
      <DSRDZ value="天津市河西区围堤道健强里17门407室" nameCN="当事人地址" />
      <DTQK value="到庭" nameCN="到庭情况" />
      <DWZWFZ nameCN="单位职务分组">
        <ZW value="退休职工" nameCN="职务" />
      </DWZWFZ>
      <DSRSFZH value="否" nameCN="当事人是否再婚" />
    </SSCYR>
    <SSCYR value="法定代理人刘婧，女，1985年1月16日出生，汉族，河北省北华航天工业学院学生，住同原告。" nameCN="诉讼参与人">
      <SSCYRMC value="刘婧" nameCN="诉讼参与人名称" />
      <SSSF value="法定代理人" nameCN="诉讼身份" />
      <DSRLX value="自然人" nameCN="当事人类型" />
      <XB value="女" nameCN="性别" />
      <MZ value="汉族" nameCN="民族" />
      <CSRQ value="1985年1月16日" nameCN="出生日期">
        <Year value="1985" nameCN="年" />
        <Month value="1" nameCN="月" />
        <Day value="16" nameCN="日" />
      </CSRQ>
      <GJ value="中国" nameCN="国籍" />
      <DSRDZ value="同原告" nameCN="当事人地址" />
    </SSCYR>
    <SSCYR value="被告刘连发，男，1953年4月29日出生，汉族，天津市建筑公司第二分公司工人，住同原告。" nameCN="诉讼参与人">
      <SSCYRMC value="刘连发" nameCN="诉讼参与人名称" />
      <SSSF value="被告" nameCN="诉讼身份" />
      <SSDW value="被告" nameCN="诉讼地位" />
      <DSRLB value="被告" nameCN="当事人类别" />
      <DSRLX value="自然人" nameCN="当事人类型" />
      <XB value="男" nameCN="性别" />
      <MZ value="汉族" nameCN="民族" />
      <CSRQ value="1953年4月29日" nameCN="出生日期">
        <Year value="1953" nameCN="年" />
        <Month value="4" nameCN="月" />
        <Day value="29" nameCN="日" />
      </CSRQ>
      <GJ value="中国" nameCN="国籍" />
      <DSRDZ value="同原告" nameCN="当事人地址" />
      <DTQK value="到庭" nameCN="到庭情况" />
      <DWZWFZ nameCN="单位职务分组">
        <ZW value="工人" nameCN="职务" />
      </DWZWFZ>
      <DSRSFZH value="否" nameCN="当事人是否再婚" />
    </SSCYR>
    <SSCYRQJ value="错误" nameCN="保险公司是否作为被告" />
  </SSCYRQJ>
  <SSJL value="原告曹玉慧与被告刘连发离婚纠纷一案，本院于2007年4月16日立案受理后，依法由代理审判员王承铭适用简易程序，公开开庭进行了审理。原告曹玉慧、被告刘连发均到庭参加了诉讼，本案现已审理终结。" nameCN="诉讼记录">
    <AY value="离婚纠纷" nameCN="案由" />
    <KTSL value="是" nameCN="开庭审理" />
    <KTSLXX value="公开审理" nameCN="开庭审理信息" />
    <WZAY value="离婚纠纷" nameCN="完整案由" />
    <AYDM value="9015" nameCN="案由代码" />
    <LARQ value="2007年4月16日" nameCN="立案日期" />
    <YSAJSYCX value="简易程序" nameCN="一审案件适用程序" />
    <JYZPT value="否" nameCN="简易转普通" />
    <YSAJLY value="新收" nameCN="一审案件来源" />
    <SLRQ value="2007年4月16日" nameCN="受理日期" />
    <CTDSRXX nameCN="出庭当事人信息">
      <CTRXM value="刘连发" nameCN="出庭人姓名">
        <SSDW value="被告" nameCN="诉讼地位" />
      </CTRXM>
      <CTRXM value="曹玉慧" nameCN="出庭人姓名">
        <SSDW value="原告" nameCN="诉讼地位" />
      </CTRXM>
    </CTDSRXX>
  </SSJL>
  <AJJBQK value="原告曹玉慧诉称，我与被告婚后经常因琐事发生矛盾。被告对我进行殴打，给我及子女造成严重伤害。我曾于2006年6月起诉离婚，被判决驳回。后双方仍无法共同生活，夫妻感情已彻底破裂，故起诉要求与被告离婚。 被告辩称，我与原告婚后虽因琐事闹矛盾，我确实也曾动手打过原告，但单亲家庭对孩子影响不好，故我不同意离婚。如果孩子能够接受，我就同意离婚。 经审理查明，原、被告于1982年经人介绍相识恋爱。1983年1月14日登记结婚，1985年1月16日生一女名刘婧。双方婚前及婚后初期感情尚可，后因生活琐事双方发生矛盾，致使之间产生隔阂。原告曾于2006年6月诉至本院，要求与被告离婚。经判决驳回。双方仍未和好，故原告再次以夫妻感情破裂为由诉至本院，要求与被告离婚。 另查，原、被告无婚前财产、婚后共同财产为海尔空调一台、西门子电冰箱一台、4组组合家具一套、写字台一件、双人床一张、单人床一张、抽油烟机架子一个、书架一个。双方现居住原告名下坐落在天津市河西区健强里17门407-413室公产房屋一套。 上述事实有原、被告当庭陈述、公有住房租赁合同、（2006）西民二初字第178号民事判决书为证，本院予以确认。" nameCN="案件基本情况">
    <YGSCD value="原告曹玉慧诉称，我与被告婚后经常因琐事发生矛盾。被告对我进行殴打，给我及子女造成严重伤害。我曾于2006年6月起诉离婚，被判决驳回。后双方仍无法共同生活，夫妻感情已彻底破裂，故起诉要求与被告离婚。 " nameCN="原告诉称段" />
    <SGXQ value="未提及" nameCN="事故详情">
      <SGSJ value="未提及" nameCN="事故时间" />
      <SGDD value="未提及" nameCN="事故地点" />
    </SGXQ>
    <JDCSYR value="刘连发" nameCN="机动车所有人" />
    <SHRJZD value="天津市河西区围堤道健强里17门407室" nameCN="受害人居住地" />
    <SHRZY value="退休职工" nameCN="受害人职业" />
    <BGBCD value="被告辩称，我与原告婚后虽因琐事闹矛盾，我确实也曾动手打过原告，但单亲家庭对孩子影响不好，故我不同意离婚。如果孩子能够接受，我就同意离婚。 " nameCN="被告辩称段" />
    <CMSSD value="经审理查明，原、被告于1982年经人介绍相识恋爱。1983年1月14日登记结婚，1985年1月16日生一女名刘婧。双方婚前及婚后初期感情尚可，后因生活琐事双方发生矛盾，致使之间产生隔阂。原告曾于2006年6月诉至本院，要求与被告离婚。经判决驳回。双方仍未和好，故原告再次以夫妻感情破裂为由诉至本院，要求与被告离婚。另查，原、被告无婚前财产、婚后共同财产为海尔空调一台、西门子电冰箱一台、4组组合家具一套、写字台一件、双人床一张、单人床一张、抽油烟机架子一个、书架一个。双方现居住原告名下坐落在天津市河西区健强里17门407-413室公产房屋一套。 上述事实有原、被告当庭陈述、公有住房租赁合同、（2006）西民二初字第178号民事判决书为证，本院予以确认。 " nameCN="查明事实段" />
  </AJJBQK>
  <CPFXGC value="本院认为，原、被告虽系自由恋爱、自主结婚，但婚后不注重夫妻感情的培养，经常因琐事发生矛盾，并有被告殴打原告现象的发生。如再勉强维系，对双方均无益。故对原告要求与被告离婚的诉讼请求，本院予以支持。关于财产，本院依法分割。关于住房，因双方均不能出资安置对方，应分室居住为宜。关于原告要求被告给付子女学费的诉讼请求，因其子女已独立生活，故本院不予支持。另对原告要求被告赔偿的诉讼请求，不符合法律规定，故不予支持。综上依据《中华人民共和国婚姻法》第三十二条第二款、第三十九条第一款之规定，判决如下：" nameCN="裁判分析过程">
    <JAFSLX value="判决" nameCN="结案方式类型" />
    <FLFTMC value="中华人民共和国婚姻法" nameCN="法律法条名称">
      <TM value="三十二" nameCN="条目">
        <KM value="第二款" nameCN="款目" />
      </TM>
      <TM value="三十九" nameCN="条目">
        <KM value="第一款" nameCN="款目" />
      </TM>
    </FLFTMC>
  </CPFXGC>
  <CPJG value="一、准予原告曹玉慧与被告刘连发离婚。 二、坐落在天津市河西区围堤道健强里17门407-413室公产房屋一套，408室房屋（大间）由原告曹玉慧租住、407室房屋（小间）由被告刘连发租住。 三、婚后共同财产海尔空调一台、西门子电冰箱一台、4组组合家具一套、单人床一张、归原告所有。书架一个、写字台一件、双人床一张、抽油烟机架子一个归被告刘连发所有。 四、驳回原告曹玉慧要求被告刘连发赔偿的诉讼请求。 五、驳回原告曹玉慧要求被告刘连发支付子女学费的诉讼请求。 案件受理费200元减半收取，由原告曹玉慧负担50元，被告刘连发负担50元（此款于本判决生效之日起5日内履行）。 如不服本判决，可在判决书送达之日起十五日内向本院提出上诉，并按对方当事人的人数提出副本，上诉于天津市第二中级人民法院。" nameCN="裁判结果">
    <JAFS value="判决" nameCN="结案方式" />
    <PCSFSXZQ value="正确" nameCN="同时起诉侵权人与保险公司的赔偿顺序" />
    <JTPJJG value="一、准予原告曹玉慧与被告刘连发离婚。" nameCN="具体裁判段" />
    <JTPJJG value="二、坐落在天津市河西区围堤道健强里17门407-413室公产房屋一套，408室房屋（大间）由原告曹玉慧租住、407室房屋（小间）由被告刘连发租住。" nameCN="具体裁判段" />
    <JTPJJG value="三、婚后共同财产海尔空调一台、西门子电冰箱一台、4组组合家具一套、单人床一张、归原告所有。书架一个、写字台一件、双人床一张、抽油烟机架子一个归被告刘连发所有。" nameCN="具体裁判段" />
    <JTPJJG value="四、驳回原告曹玉慧要求被告刘连发赔偿的诉讼请求。" nameCN="具体裁判段" />
    <JTPJJG value="五、驳回原告曹玉慧要求被告刘连发支付子女学费的诉讼请求。" nameCN="具体裁判段" />
    <SSFCD nameCN="诉讼费承担">
      <SSFCDJL value="案件受理费200元减半收取，由原告曹玉慧负担50元，被告刘连发负担50元（此款于本判决生效之日起5日内履行）。" nameCN="诉讼费承担记录">
        <SSFJE value="由原告曹玉慧负担50元" nameCN="诉讼费金额" />
        <SSFZL value="受理费" nameCN="诉讼费种类" />
        <SSFCDR value="曹玉慧" nameCN="承担人">
          <SSFCDJE value="50元" nameCN="承担金额" />
          <SSFCDFS value="个人独立承担该金额" nameCN="承担方式" />
          <SSFCDDW value="原告" nameCN="承担人地位" />
        </SSFCDR>
        <SSFCDR value="刘连发" nameCN="承担人">
          <SSFCDJE value="50元" nameCN="承担金额" />
          <SSFCDFS value="个人独立承担该金额" nameCN="承担方式" />
          <SSFCDDW value="被告" nameCN="承担人地位" />
        </SSFCDR>
      </SSFCDJL>
    </SSFCD>
    <SFFHCS value="否" nameCN="是否发回重审" />
    <KSSZ value="天津市第二中级人民法院" nameCN="可上诉至" />
    <SSQX value="十五日" nameCN="上诉期限" />
    <TCGXQYY value="否" nameCN="是否提出管辖权异议" />
  </CPJG>
  <WW value="代理审判员王承铭 二零零七年月日 书记员陈爱迪 " nameCN="文尾">
    <SPZZCY nameCN="审判组织成员">
      <SPRYXM value="王承铭" nameCN="审判人员姓名" />
      <SPRYJS value="代理审判员" nameCN="审判人员角色" />
    </SPZZCY>
    <SPZZCY nameCN="审判组织成员">
      <SPRYXM value="陈爱迪" nameCN="审判人员姓名" />
      <SPRYJS value="书记员" nameCN="审判人员角色" />
    </SPZZCY>
  </WW>
</QW>

