<?xml version="1.0" encoding="UTF-8"?>
<QW value="天津市蓟县人民法院&#xD;&#xA;民 事 判 决 书&#xD;&#xA;                      （2016）津0225民初8720号&#xD;&#xA;原告：应彩荣，女，1982年11月26日出生，汉族，农民，住蓟县马伸桥镇赵各庄村6区11排8号，现住蓟县渔阳镇五十八间新区10-1-101。&#xD;&#xA;被告：康建波，男，1982年7月16日出生，汉族，农民，住蓟县马伸桥镇赵各庄村6区11排8号。&#xD;&#xA;原告应彩荣与被告康建波离婚纠纷一案，本院受理后，依法适用简易程序，公开开庭进行了审理。原告应彩荣、被告康建波到庭参加诉讼。本案现已审理终结。&#xD;&#xA;应彩荣向本院提出诉讼请求：1、请求依法判令原、被告离婚；2、婚生子康泽堃归被告抚养，婚生女康泽珺由原告抚养，互不给付抚养费；3、诉讼费用由被告承担。事实和理由：原、被告自小相识，两家关系很好。2000年11月，经双方父母同意，原、被告订婚，2005年5月31日登记结婚。婚后双方关系良好，并生有一子康泽堃（2003年8月27日出生），一女康泽珺（2009年2月17日出生）。2014年，原告发现被告与其他女人关系暧昧，双方发生矛盾。原告考虑到双方原来感情较好，且有孩子，原告一忍再忍，并劝说被告改过，被告承诺重新做人，改善夫妻关系，然而被告根本不思悔改。随后被告又开始网上赌博，因此拖欠了部分赌债，一些赌债已由被告父母偿还，为此原、被告矛盾升级，婚姻已名存实亡。&#xD;&#xA;康建波辩称，原告所述相识、订婚、登记结婚及孩子出生时间均属实。原告所述两年前双方产生矛盾的原因属实，但被告早已改正错误。原告称被告曾欠下赌债由父母偿还的事实不存在。由于双方自小相识，结婚后夫妻感情较好，又有孩子，故不同意离婚。&#xD;&#xA;本院经审理认定事实如下：对于当事人双方没有争议的事实，本院予以确认。原告诉称被告在网上赌博，并拖欠了部分赌债，一些赌债已由被告父母偿还，但原告并未提供证据证明，且被告予以否认，本院对该部分事实不予确认。&#xD;&#xA;本院认为，原、被告自幼相识，婚前彼此充分了解，婚姻基础牢固；婚后感情较好，并育有一子一女。在共同生活中，双方应珍惜夫妻感情，理性处理生活中的矛盾，以维护家庭的完整和婚姻家庭关系的稳定。本案中，双方因生活琐事产生矛盾，只要双方互相理解和谅解，给予对方改正缺点、不足的机会，夫妻是能够和好的。本院本着有利于婚姻家庭关系的稳定及未成年子女的成长教育，又鉴于原告就夫妻感情确已彻底破裂的事实未能提供充分证据加以证明。&#xD;&#xA;综上，本院对原告的离婚请求不予支持。案经调解未果，依照《中华人民共和国婚姻法》第三十二条之规定，判决如下：&#xD;&#xA;驳回原告应彩荣的离婚诉讼请求&#xD;&#xA;案件受理费100元，由原告负担。&#xD;&#xA;如不服本判决，可在判决书送达之日起十五日内，向本院递交上诉状，并按对方当事人的人数提出副本，上诉于天津市第一中级人民法院。&#xD;&#xA;                         审  判  员    王晓东&#xD;&#xA;二〇一六年十月十一日&#xD;&#xA;书  记  员    李  杨&#xD;&#xA;附：本裁判文书所依据法律规定的具体条文&#xD;&#xA;《中华人民共和国婚姻法》第三十二条：男女一方要求离婚的，可由有关部门进行调解或直接向人民法院提出离婚诉讼。&#xD;&#xA;人民法院审理离婚案件，应当进行调解；如感情确已破裂，调解无效，应准予离婚。&#xD;&#xA;有下列情形之一，调解无效的，应准予离婚：&#xD;&#xA;（1）&#x9;重婚或有配偶者与他人同居的；&#xD;&#xA;（1）&#x9;实施家庭暴力或虐待、遗弃家庭成员的；&#xD;&#xA;（1）&#x9;有赌博、吸毒等恶习屡教不改的；&#xD;&#xA;（1）&#x9;因感情不和分居满二年的；&#xD;&#xA;（1）&#x9;其他导致夫妻感情破裂的情形。&#xD;&#xA;一方被宣告失踪，另一方提出离婚诉讼的，应准予离婚。&#xD;&#xA;PAGE  &#xD;&#xA;3&#xD;" nameCN="全文">
  <WS value="天津市蓟县人民法院 民事判决书 （2016）津0225民初8720号" nameCN="文首">
    <WSZZDW value="法院" nameCN="文书制作单位" />
    <JBFY value="天津市蓟县人民法院" nameCN="经办法院">
      <FYJB value="基层" nameCN="法院级别" />
      <XZQH_P value="天津" nameCN="行政区划(省)" />
    </JBFY>
    <WSMC value="民事判决书" nameCN="文书名称" />
    <AH value="（2016）津0225民初8720号" nameCN="案号" />
    <LAND value="2016" nameCN="立案年度" />
    <AJXZ value="民事案件" nameCN="案件性质" />
    <WSZL value="判决书" nameCN="文书种类" />
    <SPCX value="一审案件" nameCN="审判程序" />
    <AJLX value="民事一审案件" nameCN="案件类型" />
  </WS>
  <SSCYRQJ value="原告：应彩荣，女，1982年11月26日出生，汉族，农民，住蓟县马伸桥镇赵各庄村6区11排8号，现住蓟县渔阳镇五十八间新区10-1-101。 被告：康建波，男，1982年7月16日出生，汉族，农民，住蓟县马伸桥镇赵各庄村6区11排8号。" nameCN="诉讼参与人全集">
    <SSCYR value="原告：应彩荣，女，1982年11月26日出生，汉族，农民，住蓟县马伸桥镇赵各庄村6区11排8号，现住蓟县渔阳镇五十八间新区10-1-101。" nameCN="诉讼参与人">
      <SSCYRMC value="应彩荣" nameCN="诉讼参与人名称" />
      <SSSF value="原告" nameCN="诉讼身份" />
      <SSDW value="原告" nameCN="诉讼地位" />
      <DSRLB value="原告" nameCN="当事人类别" />
      <DSRLX value="自然人" nameCN="当事人类型" />
      <XB value="女" nameCN="性别" />
      <MZ value="汉族" nameCN="民族" />
      <CSRQ value="1982年11月26日" nameCN="出生日期">
        <Year value="1982" nameCN="年" />
        <Month value="11" nameCN="月" />
        <Day value="26" nameCN="日" />
      </CSRQ>
      <GJ value="中国" nameCN="国籍" />
      <DSRDZ value="蓟县渔阳镇五十八间新区10-1-101" nameCN="当事人地址" />
      <DTQK value="到庭" nameCN="到庭情况" />
      <DWZWFZ nameCN="单位职务分组">
        <ZW value="农民" nameCN="职务" />
      </DWZWFZ>
      <DSRSFZH value="否" nameCN="当事人是否再婚" />
    </SSCYR>
    <SSCYR value="被告：康建波，男，1982年7月16日出生，汉族，农民，住蓟县马伸桥镇赵各庄村6区11排8号。" nameCN="诉讼参与人">
      <SSCYRMC value="康建波" nameCN="诉讼参与人名称" />
      <SSSF value="被告" nameCN="诉讼身份" />
      <SSDW value="被告" nameCN="诉讼地位" />
      <DSRLB value="被告" nameCN="当事人类别" />
      <DSRLX value="自然人" nameCN="当事人类型" />
      <XB value="男" nameCN="性别" />
      <MZ value="汉族" nameCN="民族" />
      <CSRQ value="1982年7月16日" nameCN="出生日期">
        <Year value="1982" nameCN="年" />
        <Month value="7" nameCN="月" />
        <Day value="16" nameCN="日" />
      </CSRQ>
      <GJ value="中国" nameCN="国籍" />
      <DSRDZ value="蓟县马伸桥镇赵各庄村6区11排8号" nameCN="当事人地址" />
      <DTQK value="到庭" nameCN="到庭情况" />
      <DWZWFZ nameCN="单位职务分组">
        <ZW value="农民" nameCN="职务" />
      </DWZWFZ>
      <DSRSFZH value="否" nameCN="当事人是否再婚" />
    </SSCYR>
    <SSCYRQJ value="错误" nameCN="保险公司是否作为被告" />
  </SSCYRQJ>
  <SSJL value="原告应彩荣与被告康建波离婚纠纷一案，本院受理后，依法适用简易程序，公开开庭进行了审理。原告应彩荣、被告康建波到庭参加诉讼。本案现已审理终结。" nameCN="诉讼记录">
    <AY value="离婚纠纷" nameCN="案由" />
    <KTSL value="是" nameCN="开庭审理" />
    <KTSLXX value="公开审理" nameCN="开庭审理信息" />
    <WZAY value="离婚纠纷" nameCN="完整案由" />
    <AYDM value="9015" nameCN="案由代码" />
    <YSAJSYCX value="简易程序" nameCN="一审案件适用程序" />
    <JYZPT value="否" nameCN="简易转普通" />
    <SPZZ value="独任庭" nameCN="审判组织" />
    <YSAJLY value="新收" nameCN="一审案件来源" />
    <CTDSRXX nameCN="出庭当事人信息">
      <CTRXM value="应彩荣" nameCN="出庭人姓名">
        <SSDW value="原告" nameCN="诉讼地位" />
      </CTRXM>
      <CTRXM value="康建波" nameCN="出庭人姓名">
        <SSDW value="被告" nameCN="诉讼地位" />
      </CTRXM>
    </CTDSRXX>
  </SSJL>
  <AJJBQK value="应彩荣向本院提出诉讼请求：1、请求依法判令原、被告离婚；2、婚生子康泽堃归被告抚养，婚生女康泽珺由原告抚养，互不给付抚养费；3、诉讼费用由被告承担。事实和理由：原、被告自小相识，两家关系很好。2000年11月，经双方父母同意，原、被告订婚，2005年5月31日登记结婚。婚后双方关系良好，并生有一子康泽堃（2003年8月27日出生），一女康泽珺（2009年2月17日出生）。2014年，原告发现被告与其他女人关系暧昧，双方发生矛盾。原告考虑到双方原来感情较好，且有孩子，原告一忍再忍，并劝说被告改过，被告承诺重新做人，改善夫妻关系，然而被告根本不思悔改。随后被告又开始网上赌博，因此拖欠了部分赌债，一些赌债已由被告父母偿还，为此原、被告矛盾升级，婚姻已名存实亡。 康建波辩称，原告所述相识、订婚、登记结婚及孩子出生时间均属实。原告所述两年前双方产生矛盾的原因属实，但被告早已改正错误。原告称被告曾欠下赌债由父母偿还的事实不存在。由于双方自小相识，结婚后夫妻感情较好，又有孩子，故不同意离婚。 本院经审理认定事实如下：对于当事人双方没有争议的事实，本院予以确认。原告诉称被告在网上赌博，并拖欠了部分赌债，一些赌债已由被告父母偿还，但原告并未提供证据证明，且被告予以否认，本院对该部分事实不予确认。" nameCN="案件基本情况">
    <YGSCD value="应彩荣向本院提出诉讼请求：1、请求依法判令原、被告离婚；2、婚生子康泽堃归被告抚养，婚生女康泽珺由原告抚养，互不给付抚养费；3、诉讼费用由被告承担。事实和理由：原、被告自小相识，两家关系很好。2000年11月，经双方父母同意，原、被告订婚，2005年5月31日登记结婚。婚后双方关系良好，并生有一子康泽堃（2003年8月27日出生），一女康泽珺（2009年2月17日出生）。2014年，原告发现被告与其他女人关系暧昧，双方发生矛盾。原告考虑到双方原来感情较好，且有孩子，原告一忍再忍，并劝说被告改过，被告承诺重新做人，改善夫妻关系，然而被告根本不思悔改。随后被告又开始网上赌博，因此拖欠了部分赌债，一些赌债已由被告父母偿还，为此原、被告矛盾升级，婚姻已名存实亡。 " nameCN="原告诉称段" />
    <SGXQ value="未提及" nameCN="事故详情">
      <SGSJ value="未提及" nameCN="事故时间" />
      <SGDD value="未提及" nameCN="事故地点" />
    </SGXQ>
    <JDCSYR value="康建波" nameCN="机动车所有人" />
    <GAJGRDYJ value="对于当事人双方没有争议的事实，本院予以确认。" nameCN="公安机关认定意见" />
    <SHRJZD value="蓟县渔阳镇五十八间新区10-1-101" nameCN="受害人居住地" />
    <SHRZY value="农民" nameCN="受害人职业" />
    <BGBCD value="康建波辩称，原告所述相识、订婚、登记结婚及孩子出生时间均属实。原告所述两年前双方产生矛盾的原因属实，但被告早已改正错误。原告称被告曾欠下赌债由父母偿还的事实不存在。由于双方自小相识，结婚后夫妻感情较好，又有孩子，故不同意离婚。 " nameCN="被告辩称段" />
    <CMSSD value="本院经审理认定事实如下：对于当事人双方没有争议的事实，本院予以确认。原告诉称被告在网上赌博，并拖欠了部分赌债，一些赌债已由被告父母偿还，但原告并未提供证据证明，且被告予以否认，本院对该部分事实不予确认。" nameCN="查明事实段" />
  </AJJBQK>
  <CPFXGC value="本院认为，原、被告自幼相识，婚前彼此充分了解，婚姻基础牢固；婚后感情较好，并育有一子一女。在共同生活中，双方应珍惜夫妻感情，理性处理生活中的矛盾，以维护家庭的完整和婚姻家庭关系的稳定。本案中，双方因生活琐事产生矛盾，只要双方互相理解和谅解，给予对方改正缺点、不足的机会，夫妻是能够和好的。本院本着有利于婚姻家庭关系的稳定及未成年子女的成长教育，又鉴于原告就夫妻感情确已彻底破裂的事实未能提供充分证据加以证明。 综上，本院对原告的离婚请求不予支持。案经调解未果，依照《中华人民共和国婚姻法》第三十二条之规定，判决如下：" nameCN="裁判分析过程">
    <JAFSLX value="判决" nameCN="结案方式类型" />
    <FLFTMC value="中华人民共和国婚姻法" nameCN="法律法条名称">
      <TM value="三十二" nameCN="条目" />
    </FLFTMC>
  </CPFXGC>
  <CPJG value="驳回原告应彩荣的离婚诉讼请求案件受理费100元，由原告负担。 如不服本判决，可在判决书送达之日起十五日内，向本院递交上诉状，并按对方当事人的人数提出副本，上诉于天津市第一中级人民法院。" nameCN="裁判结果">
    <JAFS value="判决" nameCN="结案方式" />
    <PCSFSXZQ value="正确" nameCN="同时起诉侵权人与保险公司的赔偿顺序" />
    <JTPJJG value="驳回原告应彩荣的离婚诉讼请求案件受理费100元，由原告负担。" nameCN="具体裁判段">
      <PJJE nameCN="判决金额">
        <JE value="100元" nameCN="金额" />
      </PJJE>
    </JTPJJG>
    <JTPJJG value="如不服本判决，可在判决书送达之日起十五日内，向本院递交上诉状，并按对方当事人的人数提出副本，上诉于天津市第一中级人民法院。" nameCN="具体裁判段" />
    <SFFHCS value="否" nameCN="是否发回重审" />
    <KSSZ value="天津市第一中级人民法院" nameCN="可上诉至" />
    <SSTJCL value="上诉状，并按对方当事人的人数提出副本" nameCN="上诉提交材料" />
    <SSQX value="十五日" nameCN="上诉期限" />
    <TCGXQYY value="否" nameCN="是否提出管辖权异议" />
  </CPJG>
  <WW value="审判员王晓东 二〇一六年十月十一日 书记员李杨" nameCN="文尾">
    <SPZZCY nameCN="审判组织成员">
      <SPRYXM value="王晓东" nameCN="审判人员姓名" />
      <SPRYJS value="审判员" nameCN="审判人员角色" />
    </SPZZCY>
    <SPZZCY nameCN="审判组织成员">
      <SPRYXM value="李杨" nameCN="审判人员姓名" />
      <SPRYJS value="书记员" nameCN="审判人员角色" />
    </SPZZCY>
    <CPSJ value="2016年10月11日" nameCN="裁判时间">
      <Year value="2016" nameCN="结案年度" />
      <JANYR value="2016年10月11日" nameCN="结案年月日" />
      <JANY value="2016-10" nameCN="结案年月" />
      <Month value="10" nameCN="月" />
      <Day value="11" nameCN="日" />
    </CPSJ>
  </WW>
  <FL value="附：本裁判文书所依据法律规定的具体条文 《中华人民共和国婚姻法》第三十二条：男女一方要求离婚的，可由有关部门进行调解或直接向人民法院提出离婚诉讼。 人民法院审理离婚案件，应当进行调解；如感情确已破裂，调解无效，应准予离婚。 有下列情形之一，调解无效的，应准予离婚： （1）&#x9;重婚或有配偶者与他人同居的； （1）&#x9;实施家庭暴力或虐待、遗弃家庭成员的； （1）&#x9;有赌博、吸毒等恶习屡教不改的； （1）&#x9;因感情不和分居满二年的； （1）&#x9;其他导致夫妻感情破裂的情形。 一方被宣告失踪，另一方提出离婚诉讼的，应准予离婚。 一方被宣告失踪，另一方提出离婚诉讼的，应准予离婚。" nameCN="附录" />
</QW>

