<?xml version="1.0" encoding="UTF-8"?>
<QW value="天津市宝坻区人民法院&#xD;&#xA;民  事  判  决  书&#xD;&#xA;（2010）宝民初字第4169号&#xD;&#xA;原告魏志刚，男，1967年2月14日出生，汉族，农民，住天津市宝坻区海滨街道苏北路18—1号。&#xD;&#xA;委托代理人王连红，天津市宝信律师事务所律师。&#xD;&#xA;被告张金华，女，1967年5月9日出生，汉族，农民，原住址同上，现住天津市宝坻区华苑东区37—2—201室。&#xD;&#xA;委托代理人王学义，北京市浩林律师事务所律师。&#xD;&#xA;原告魏志刚与被告张金华离婚纠纷一案，本院于2010年11月19日受理后，依法由代理审判员何玉江独任审判，后因案情复杂转为普通程序审理。因此案的审理需以他案的审理结果为依据，故此案于2010年12月3日中止审理，中止原因消除后于2011年4月21日恢复并不公开开庭进行了审理，原、被告及双方委托代理人到庭参加诉讼。本案现已审理终结。&#xD;&#xA;原告诉称，原、被告经人介绍相识，于1992年5月1日登记结婚。1993年9月5日生育长女魏灵雨，现魏灵雨在宝坻卫校读书。2002年4月24日生育长子魏中正。婚后原、被告一直与原告父母共同生活。双方因性格不投，多年来经常争吵。尤其自2005年9月以来，被告更是无端找茬与原告吵闹，怀疑原告且限制原告的正常经营行为。虽经亲友劝说，但被告仍不能很好的理解原告，仍旧继续与原告争吵。后被告竟离开家回到娘家居住至今。显然双方感情早已破裂，原告曾于2006年11月向宝坻法院起诉，经法庭劝说，原告撤诉。但在原告撤诉后，被告并未返回家中，反而提起离婚诉讼，在法庭审理过程中，因涉及到原告家庭共有财产的析产分割问题，该离婚诉讼曾中止审理，但在法庭恢复审理后，被告却没有出庭，法庭按撤诉处理。2009年4月，原告向宝坻区法院起诉离婚，2010年5月11日原告撤诉，撤诉后原、被告仍无联系。从2005年至今，原、被告一直分居，互不履行夫妻义务，故起诉要求：1、准予原告与被告离婚；2、婚生女魏灵雨、婚生子魏中正随原告生活，被告每月负担抚育费各500元，至子女独立生活时止；3、诉讼费用由被告负担。&#xD;&#xA;被告辩称，原、被告于1988年相识，双方在宝坻卫生学校上学期间恋爱，毕业后共同开办医疗诊所，后于1992年5月登记结婚。双方婚后感情很好，但自2005年起原告与他人有暧昧关系双方开始发生争吵，但双方感情并未破裂。现双方生育两子女，且两子女亦不同意原、被告离婚，故不同意原告的诉讼请求。&#xD;&#xA;经审理查明，原、被告于1988年在宝坻卫生学校上学期间相识并确立恋爱关系，1992年5月1日登记结婚。双方于1993年9月5日生育长女魏灵雨。2002年4月24日生育长子魏中正。双方婚后感情较好，后因生活琐事发生矛盾。2006年11月原告曾向宝坻法院起诉离婚，后撤诉。原告撤诉后，被告亦向本院提起离婚诉讼，后被告未按时到庭参加诉讼，按撤诉处理。2009年4月，原告再次向本院起诉离婚，后撤诉。后原告再次以前述理由起诉要求离婚。&#xD;&#xA;在本案审理中，双方之女魏灵雨向本院书面陈述：“宝坻区法院审判长：我听我妈说您在审理我爸起诉离婚的事，我向您含泪哭诉，我本心非常不同意父母离婚，我们一家还是个完整的家庭，不管爸爸妈妈谁对谁错，请您劝他们互谅互让，还是能够弥补裂痕的。……”双方之子魏中正向本院书面陈述： “法官老师……我听说我爸要和我妈离婚，我真不想他们分开，那样我就成单亲的孩子了，我心里受不了。我求求法官老师劝劝我爸别离婚了……”&#xD;&#xA;本院认为，双方婚前认识时间较长，在上学期间就建立了恋爱关系，此期间有深厚的感情基础。双方于1992年5月1日登记结婚后同居生活，应是在深厚的感情基础上经过深思熟虑所产生的必然结果。双方结婚多年，婚后感情较好，已建立起来的多年的夫妻感情双方均应珍惜。双方婚后生育两子女，两子女亦向本院表达了希望父母和好、家庭完整的强烈愿望，抚养教育子女是每一个作为父母的权利，更是应尽的义务。父母离异后，子女的精神健康、心理状态等都会受到不可估量的伤害，因此原、被告在处理婚姻问题上均应慎重且应更多考虑子女利益。双方虽曾几次在本院提起离婚诉讼，但均是以撤诉或者本院裁定撤诉结案，也说明了双方早已建立起来的夫妻感情尚在。现双方只要相互多一些关心、多一些尊重和沟通、努力改善夫妻关系并为子女利益着想，目前夫妻关系尚可改善。此案经调解，原告坚持离婚，但其起诉离婚证据不足。综上所述，依据《中华人民共和国婚姻法》第三十二条第二款、最高人民法院《关于民事诉讼证据的若干规定》第二条的规定，判决如下：&#xD;&#xA;驳回原告魏志刚离婚之诉讼请求。&#xD;&#xA;    诉讼费用200元由原告负担（原告已缴纳）。&#xD;&#xA;如不服本判决，可在收到判决书之日起十五日内向本院递交上诉状，并按对方当事人的人数提出副本，上诉于天津市第一中级人民法院。&#xD;&#xA;审  判  长  孙少杰&#xD;&#xA;代理审判员  张建新&#xD;&#xA;代理审判员  何玉江&#xD;&#xA;二〇一一年七月  日&#xD;&#xA;书  记  员  赵  静&#xD;&#xA;附相关法律规定：&#xD;&#xA;《中华人民共和国婚姻法》第三十二条第二款：&#xD;&#xA;人民法院审理离婚案件，应当进行调解；如感情确已破裂，调解无效，应准予离婚。&#xD;&#xA;最高人民法院《关于民事诉讼证据的若干规定》第二条：当事人对自己提出的诉讼请求所依据的事实或者反驳对方诉讼请求所依据的事实有责任提供证据加以证明。&#xD;&#xA;没有证据或者证据不足以证明当事人的事实主张的，由负有举证责任的当事人承担不利后果。&#xD;" nameCN="全文">
  <WS value="天津市宝坻区人民法院 民事判决书 （2010）宝民初字第4169号" nameCN="文首">
    <WSZZDW value="法院" nameCN="文书制作单位" />
    <JBFY value="天津市宝坻区人民法院" nameCN="经办法院">
      <FYJB value="基层" nameCN="法院级别" />
      <XZQH_P value="天津" nameCN="行政区划(省)" />
    </JBFY>
    <WSMC value="民事判决书" nameCN="文书名称" />
    <AH value="（2010）宝民初字第4169号" nameCN="案号" />
    <LAND value="2010" nameCN="立案年度" />
    <AJXZ value="民事案件" nameCN="案件性质" />
    <WSZL value="判决书" nameCN="文书种类" />
    <SPCX value="一审案件" nameCN="审判程序" />
    <AJLX value="民事一审案件" nameCN="案件类型" />
  </WS>
  <SSCYRQJ value="原告魏志刚，男，1967年2月14日出生，汉族，农民，住天津市宝坻区海滨街道苏北路18—1号。 委托代理人王连红，天津市宝信律师事务所律师。 被告张金华，女，1967年5月9日出生，汉族，农民，原住址同上，现住天津市宝坻区华苑东区37—2—201室。 委托代理人王学义，北京市浩林律师事务所律师。" nameCN="诉讼参与人全集">
    <SSCYR value="原告魏志刚，男，1967年2月14日出生，汉族，农民，住天津市宝坻区海滨街道苏北路18—1号。" nameCN="诉讼参与人">
      <SSCYRMC value="魏志刚" nameCN="诉讼参与人名称" />
      <SSSF value="原告" nameCN="诉讼身份" />
      <SSDW value="原告" nameCN="诉讼地位" />
      <DSRLB value="原告" nameCN="当事人类别" />
      <DSRLX value="自然人" nameCN="当事人类型" />
      <XB value="男" nameCN="性别" />
      <MZ value="汉族" nameCN="民族" />
      <CSRQ value="1967年2月14日" nameCN="出生日期">
        <Year value="1967" nameCN="年" />
        <Month value="2" nameCN="月" />
        <Day value="14" nameCN="日" />
      </CSRQ>
      <GJ value="中国" nameCN="国籍" />
      <DSRDZ value="天津市宝坻区海滨街道苏北路18—1号" nameCN="当事人地址" />
      <DWZWFZ nameCN="单位职务分组">
        <ZW value="农民" nameCN="职务" />
      </DWZWFZ>
      <DSRSFZH value="否" nameCN="当事人是否再婚" />
    </SSCYR>
    <SSCYR value="委托代理人王连红，天津市宝信律师事务所律师。" nameCN="诉讼参与人">
      <SSCYRMC value="王连红" nameCN="诉讼参与人名称" />
      <SSSF value="委托代理人" nameCN="诉讼身份" />
      <DSRLX value="自然人" nameCN="当事人类型" />
      <GJ value="中国" nameCN="国籍" />
      <DWZWFZ nameCN="单位职务分组">
        <ZW value="律师" nameCN="职务" />
      </DWZWFZ>
    </SSCYR>
    <SSCYR value="被告张金华，女，1967年5月9日出生，汉族，农民，原住址同上，现住天津市宝坻区华苑东区37—2—201室。" nameCN="诉讼参与人">
      <SSCYRMC value="张金华" nameCN="诉讼参与人名称" />
      <SSSF value="被告" nameCN="诉讼身份" />
      <SSDW value="被告" nameCN="诉讼地位" />
      <DSRLB value="被告" nameCN="当事人类别" />
      <DSRLX value="自然人" nameCN="当事人类型" />
      <XB value="女" nameCN="性别" />
      <MZ value="汉族" nameCN="民族" />
      <CSRQ value="1967年5月9日" nameCN="出生日期">
        <Year value="1967" nameCN="年" />
        <Month value="5" nameCN="月" />
        <Day value="9" nameCN="日" />
      </CSRQ>
      <GJ value="中国" nameCN="国籍" />
      <DSRDZ value="天津市宝坻区华苑东区37—2—201室" nameCN="当事人地址" />
      <DWZWFZ nameCN="单位职务分组">
        <ZW value="农民" nameCN="职务" />
      </DWZWFZ>
      <DSRSFZH value="否" nameCN="当事人是否再婚" />
    </SSCYR>
    <SSCYR value="委托代理人王学义，北京市浩林律师事务所律师。" nameCN="诉讼参与人">
      <SSCYRMC value="王学义" nameCN="诉讼参与人名称" />
      <SSSF value="委托代理人" nameCN="诉讼身份" />
      <DSRLX value="自然人" nameCN="当事人类型" />
      <GJ value="中国" nameCN="国籍" />
      <DWZWFZ nameCN="单位职务分组">
        <ZW value="律师" nameCN="职务" />
      </DWZWFZ>
    </SSCYR>
    <SSCYRQJ value="错误" nameCN="保险公司是否作为被告" />
  </SSCYRQJ>
  <SSJL value="原告魏志刚与被告张金华离婚纠纷一案，本院于2010年11月19日受理后，依法由代理审判员何玉江独任审判，后因案情复杂转为普通程序审理。因此案的审理需以他案的审理结果为依据，故此案于2010年12月3日中止审理，中止原因消除后于2011年4月21日恢复并不公开开庭进行了审理，原、被告及双方委托代理人到庭参加诉讼。本案现已审理终结。" nameCN="诉讼记录">
    <AY value="离婚纠纷" nameCN="案由" />
    <KTSL value="是" nameCN="开庭审理" />
    <KTSLXX value="不公开审理" nameCN="开庭审理信息">
      <BGKSLYY value="当事人申请不公开审理的离婚案件" nameCN="不公开审理原因" />
    </KTSLXX>
    <WZAY value="离婚纠纷" nameCN="完整案由" />
    <AYDM value="9015" nameCN="案由代码" />
    <LARQ value="2010年11月19日" nameCN="立案日期" />
    <YSAJSYCX value="普通程序" nameCN="一审案件适用程序" />
    <JYZPT value="是" nameCN="简易转普通" />
    <YSAJLY value="新收" nameCN="一审案件来源" />
    <SLRQ value="2010年11月19日" nameCN="受理日期" />
  </SSJL>
  <AJJBQK value="原告诉称，原、被告经人介绍相识，于1992年5月1日登记结婚。1993年9月5日生育长女魏灵雨，现魏灵雨在宝坻卫校读书。2002年4月24日生育长子魏中正。婚后原、被告一直与原告父母共同生活。双方因性格不投，多年来经常争吵。尤其自2005年9月以来，被告更是无端找茬与原告吵闹，怀疑原告且限制原告的正常经营行为。虽经亲友劝说，但被告仍不能很好的理解原告，仍旧继续与原告争吵。后被告竟离开家回到娘家居住至今。显然双方感情早已破裂，原告曾于2006年11月向宝坻法院起诉，经法庭劝说，原告撤诉。但在原告撤诉后，被告并未返回家中，反而提起离婚诉讼，在法庭审理过程中，因涉及到原告家庭共有财产的析产分割问题，该离婚诉讼曾中止审理，但在法庭恢复审理后，被告却没有出庭，法庭按撤诉处理。2009年4月，原告向宝坻区法院起诉离婚，2010年5月11日原告撤诉，撤诉后原、被告仍无联系。从2005年至今，原、被告一直分居，互不履行夫妻义务，故起诉要求：1、准予原告与被告离婚；2、婚生女魏灵雨、婚生子魏中正随原告生活，被告每月负担抚育费各500元，至子女独立生活时止；3、诉讼费用由被告负担。 被告辩称，原、被告于1988年相识，双方在宝坻卫生学校上学期间恋爱，毕业后共同开办医疗诊所，后于1992年5月登记结婚。双方婚后感情很好，但自2005年起原告与他人有暧昧关系双方开始发生争吵，但双方感情并未破裂。现双方生育两子女，且两子女亦不同意原、被告离婚，故不同意原告的诉讼请求。 经审理查明，原、被告于1988年在宝坻卫生学校上学期间相识并确立恋爱关系，1992年5月1日登记结婚。双方于1993年9月5日生育长女魏灵雨。2002年4月24日生育长子魏中正。双方婚后感情较好，后因生活琐事发生矛盾。2006年11月原告曾向宝坻法院起诉离婚，后撤诉。原告撤诉后，被告亦向本院提起离婚诉讼，后被告未按时到庭参加诉讼，按撤诉处理。2009年4月，原告再次向本院起诉离婚，后撤诉。后原告再次以前述理由起诉要求离婚。 在本案审理中，双方之女魏灵雨向本院书面陈述：“宝坻区法院审判长：我听我妈说您在审理我爸起诉离婚的事，我向您含泪哭诉，我本心非常不同意父母离婚，我们一家还是个完整的家庭，不管爸爸妈妈谁对谁错，请您劝他们互谅互让，还是能够弥补裂痕的。……”双方之子魏中正向本院书面陈述：“法官老师……我听说我爸要和我妈离婚，我真不想他们分开，那样我就成单亲的孩子了，我心里受不了。我求求法官老师劝劝我爸别离婚了……”" nameCN="案件基本情况">
    <YGSCD value="原告诉称，原、被告经人介绍相识，于1992年5月1日登记结婚。1993年9月5日生育长女魏灵雨，现魏灵雨在宝坻卫校读书。2002年4月24日生育长子魏中正。婚后原、被告一直与原告父母共同生活。双方因性格不投，多年来经常争吵。尤其自2005年9月以来，被告更是无端找茬与原告吵闹，怀疑原告且限制原告的正常经营行为。虽经亲友劝说，但被告仍不能很好的理解原告，仍旧继续与原告争吵。后被告竟离开家回到娘家居住至今。显然双方感情早已破裂，原告曾于2006年11月向宝坻法院起诉，经法庭劝说，原告撤诉。但在原告撤诉后，被告并未返回家中，反而提起离婚诉讼，在法庭审理过程中，因涉及到原告家庭共有财产的析产分割问题，该离婚诉讼曾中止审理，但在法庭恢复审理后，被告却没有出庭，法庭按撤诉处理。2009年4月，原告向宝坻区法院起诉离婚，2010年5月11日原告撤诉，撤诉后原、被告仍无联系。从2005年至今，原、被告一直分居，互不履行夫妻义务，故起诉要求：1、准予原告与被告离婚；2、婚生女魏灵雨、婚生子魏中正随原告生活，被告每月负担抚育费各500元，至子女独立生活时止；3、诉讼费用由被告负担。 " nameCN="原告诉称段">
      <SSJE nameCN="交通事故原告诉称诉讼金额">
        <SSJESL value="500元" nameCN="金额" />
      </SSJE>
    </YGSCD>
    <SGXQ value="未提及" nameCN="事故详情">
      <SGSJ value="未提及" nameCN="事故时间" />
      <SGDD value="未提及" nameCN="事故地点" />
    </SGXQ>
    <JDCSYR value="张金华" nameCN="机动车所有人" />
    <SHRJZD value="天津市宝坻区海滨街道苏北路18—1号" nameCN="受害人居住地" />
    <SHRZY value="农民" nameCN="受害人职业" />
    <BGBCD value="被告辩称，原、被告于1988年相识，双方在宝坻卫生学校上学期间恋爱，毕业后共同开办医疗诊所，后于1992年5月登记结婚。双方婚后感情很好，但自2005年起原告与他人有暧昧关系双方开始发生争吵，但双方感情并未破裂。现双方生育两子女，且两子女亦不同意原、被告离婚，故不同意原告的诉讼请求。 " nameCN="被告辩称段" />
    <CMSSD value="经审理查明，原、被告于1988年在宝坻卫生学校上学期间相识并确立恋爱关系，1992年5月1日登记结婚。双方于1993年9月5日生育长女魏灵雨。2002年4月24日生育长子魏中正。双方婚后感情较好，后因生活琐事发生矛盾。2006年11月原告曾向宝坻法院起诉离婚，后撤诉。原告撤诉后，被告亦向本院提起离婚诉讼，后被告未按时到庭参加诉讼，按撤诉处理。2009年4月，原告再次向本院起诉离婚，后撤诉。后原告再次以前述理由起诉要求离婚。在本案审理中，双方之女魏灵雨向本院书面陈述：“宝坻区法院审判长：我听我妈说您在审理我爸起诉离婚的事，我向您含泪哭诉，我本心非常不同意父母离婚，我们一家还是个完整的家庭，不管爸爸妈妈谁对谁错，请您劝他们互谅互让，还是能够弥补裂痕的。……”双方之子魏中正向本院书面陈述：“法官老师……我听说我爸要和我妈离婚，我真不想他们分开，那样我就成单亲的孩子了，我心里受不了。我求求法官老师劝劝我爸别离婚了……” " nameCN="查明事实段" />
  </AJJBQK>
  <CPFXGC value="本院认为，双方婚前认识时间较长，在上学期间就建立了恋爱关系，此期间有深厚的感情基础。双方于1992年5月1日登记结婚后同居生活，应是在深厚的感情基础上经过深思熟虑所产生的必然结果。双方结婚多年，婚后感情较好，已建立起来的多年的夫妻感情双方均应珍惜。双方婚后生育两子女，两子女亦向本院表达了希望父母和好、家庭完整的强烈愿望，抚养教育子女是每一个作为父母的权利，更是应尽的义务。父母离异后，子女的精神健康、心理状态等都会受到不可估量的伤害，因此原、被告在处理婚姻问题上均应慎重且应更多考虑子女利益。双方虽曾几次在本院提起离婚诉讼，但均是以撤诉或者本院裁定撤诉结案，也说明了双方早已建立起来的夫妻感情尚在。现双方只要相互多一些关心、多一些尊重和沟通、努力改善夫妻关系并为子女利益着想，目前夫妻关系尚可改善。此案经调解，原告坚持离婚，但其起诉离婚证据不足。综上所述，依据《中华人民共和国婚姻法》第三十二条第二款、最高人民法院《关于民事诉讼证据的若干规定》第二条的规定，判决如下：" nameCN="裁判分析过程">
    <JAFSLX value="判决" nameCN="结案方式类型" />
    <FLFTMC value="中华人民共和国婚姻法" nameCN="法律法条名称">
      <TM value="三十二" nameCN="条目">
        <KM value="第二款" nameCN="款目" />
      </TM>
    </FLFTMC>
    <FLFTMC value="关于民事诉讼证据的若干规定" nameCN="法律法条名称">
      <TM value="二" nameCN="条目" />
    </FLFTMC>
  </CPFXGC>
  <CPJG value="驳回原告魏志刚离婚之诉讼请求。 诉讼费用200元由原告负担（原告已缴纳）。 如不服本判决，可在收到判决书之日起十五日内向本院递交上诉状，并按对方当事人的人数提出副本，上诉于天津市第一中级人民法院。" nameCN="裁判结果">
    <JAFS value="判决" nameCN="结案方式" />
    <PCSFSXZQ value="正确" nameCN="同时起诉侵权人与保险公司的赔偿顺序" />
    <JTPJJG value="驳回原告魏志刚离婚之诉讼请求。" nameCN="具体裁判段" />
    <SSFCD nameCN="诉讼费承担">
      <SSFCDJL value="诉讼费用200元由原告负担（原告已缴纳）。" nameCN="诉讼费承担记录">
        <SSFJE value="200元" nameCN="诉讼费金额" />
        <SSFZL value="诉讼费用" nameCN="诉讼费种类" />
      </SSFCDJL>
    </SSFCD>
    <SFFHCS value="否" nameCN="是否发回重审" />
    <KSSZ value="天津市第一中级人民法院" nameCN="可上诉至" />
    <SSTJCL value="上诉状，并按对方当事人的人数提出副本" nameCN="上诉提交材料" />
    <TCGXQYY value="否" nameCN="是否提出管辖权异议" />
  </CPJG>
  <WW value="审判长孙少杰 代理审判员张建新 代理审判员何玉江 二〇一一年七月日 书记员赵静" nameCN="文尾">
    <SPZZCY nameCN="审判组织成员">
      <SPRYXM value="孙少杰" nameCN="审判人员姓名" />
      <SPRYJS value="审判长" nameCN="审判人员角色" />
    </SPZZCY>
    <SPZZCY nameCN="审判组织成员">
      <SPRYXM value="赵静" nameCN="审判人员姓名" />
      <SPRYJS value="书记员" nameCN="审判人员角色" />
    </SPZZCY>
    <SPZZCY nameCN="审判组织成员">
      <SPRYXM value="何玉江" nameCN="审判人员姓名" />
      <SPRYJS value="代理审判员" nameCN="审判人员角色" />
    </SPZZCY>
    <SPZZCY nameCN="审判组织成员">
      <SPRYXM value="张建新" nameCN="审判人员姓名" />
      <SPRYJS value="代理审判员" nameCN="审判人员角色" />
    </SPZZCY>
  </WW>
</QW>

