<?xml version="1.0" encoding="UTF-8"?>
<QW value="天津市宝坻区人民法院&#xD;&#xA;民事判决书&#xD;&#xA;（2015）宝民初字第4723号&#xD;&#xA;原告蒋自秀，女，1972年5月27日出生（公民身份号码120224197205275923），汉族，农民，户籍住所天津市宝坻区八门城镇欢喜庄村9排20号，现住天津市宝坻区宝平街道西南楼宿舍24栋164号。&#xD;&#xA;被告刘顺东，男，1971年4月6日出生（公民身份号码120224197104065919），汉族，农民，户籍住所天津市宝坻区八门城镇欢喜庄村9排20号，现住天津市宝坻区宝平街道西南楼宿舍24栋164号。&#xD;&#xA;原告蒋自秀与被告刘顺东离婚纠纷一案，本院于2015年5月29日立案受理后，依法由审判员郝志军独任审判，公开开庭进行了审理。原告蒋自秀、被告刘顺东到庭参加诉讼。本案现已审理终结。&#xD;&#xA;原告诉称，原、被告于1993年秋经人介绍相识并确立恋爱关系， 1994年4月6日登记结婚开始共同生活。1995年2月9生育长女刘怡，现在天津农学院读书。2003年6月25日生育长子刘鑫杨，现在宝坻区第八小学读书。被告性格固执且脾气暴躁，动辄找茬与原告打架。因感情不合原告曾在1998年提出过离婚诉讼，因被告不同意离婚被驳回了离婚的请求。原告考虑到孩子尚小，为了给孩子一个完整的家，一直忍辱负重勉强与被告生活在一起，但被告根本不知道理解原告，依然我行我素、酗酒成性，还生性多疑对原告无端怀疑直至大打出手，经常对原告施以家庭暴力。现双方没有任何感情可言，为尽早解除这段痛苦的婚姻，原告提起诉讼请求：1、依法判准原、被告离婚。2、判令原、被告之子刘鑫杨随原告生活，被告每月给付抚养费800元至其独立生活时止；原、被告之女刘怡随原告生活，被告每月给付教育费、生活费3000元。3、夫妻共同财产宝坻区八门城镇欢喜庄村村西自建门脸房价值80000元，宝坻区八门城镇欢喜庄村9排20号住宅建院墙、厢房价值30000元，夏利牌轿车1辆价值5000元，新型802DB—2推土机1台价值80000元，五羊牌摩托车1辆价值2000元，手扶拖拉机1辆价值2000元归被告所有，被告给付原告折价款100000元。 4、诉讼费用由被告承担。&#xD;&#xA;原告为支持其主张提交如下证据：原、被告结婚证复印件1份；原、被告及原、被告之女刘怡、之子刘鑫杨户口页复印件各1份；申请法院调取原告在公安宝坻分局宝平派出所询问笔录及诊断证明书，证明被告殴打原告的情况。&#xD;&#xA;被告辩称，1998年与原告闹离婚，不是因为感情不和，是因为被告的父母。这次打架责任在被告，是被告喝酒动手打了原告，对原告的伤害也挺大，在此向原告道歉，请求原告的原谅并保证以后再不喝酒了，毕竟与原告有二十多年的夫妻感情，所以不同意离婚。&#xD;&#xA;被告未提交证据。&#xD;&#xA;经审理查明，原、被告于1993年秋经人介绍相识并确立恋爱关系， 1994年4月6日登记结婚开始共同生活。1995年2月9生育长女刘怡，现在天津农学院读书。2003年6月25日生育长子刘鑫杨，现在宝坻区第八小学读书。2015年5月25日，原、被告因家庭琐事发生争吵、打架。5月29日后双方开始分居至今。&#xD;&#xA;庭审中，被告承认5月25日那天酒后与原告发生厮打，亦承认都是被告的错。&#xD;&#xA;本院认为，夫妻之间应互相尊重，互谅互让，和睦相处，为子女创建温馨和谐的家庭环境。原、被告结婚二十多年，并生育一女一子，应有较深的感情基础。在共同生活期间因琐事发生争吵，产生矛盾是很难避免的，但被告动手殴打原告是不对的，在此对被告提出批评。此案经调解原告坚持离婚，被告不同意离婚，但原告提交的证据不足以证明双方感情已彻底破裂，故对原告的请求本院不予支持。希望双方在今后的共同生活中，加强沟通，勤于交流，彼此信任，珍惜夫妻感情，以有利于子女的健康成长。依据《中华人民共和国婚姻法》第三十二条第二款，《最高人民法院关于适用&lt;中华人民共和国民事诉讼法&gt;的解释》第九十条之规定，判决如下：&#xD;&#xA;驳回原告蒋自秀离婚的诉讼请求。&#xD;&#xA;案件受理费214元，已减半收取107元（该款原告已交纳），由原告蒋自秀负担100元，其余7元退回原告蒋自秀。&#xD;&#xA;如不服本判决，可在判决书送达之日起十五日内，向本院递交上诉状，并按对方当事人的人数提出副本，上诉于天津市第一中级人民法院。&#xD;&#xA;审  判  员    郝志军&#xD;&#xA;二○一五年六月二十三日&#xD;&#xA;书  记  员    杜建玥&#xD;&#xA;附相关法律规定：&#xD;&#xA;《中华人民共和国婚姻法》&#xD;&#xA;第三十二条第二款  人民法院审理离婚案件，应当进行调解；如感情确已破裂，调解无效，应准予离婚。&#xD;&#xA;有下列情形之一，调解无效的，应准予离婚：&#xD;&#xA;（一）重婚或者有配偶者与他人同居的；&#xD;&#xA;（二）实施家庭暴力或虐待、遗弃家庭成员的；&#xD;&#xA;（三）有赌博、吸毒等恶习屡教不改的；&#xD;&#xA;（四）因感情不和分居满2年的；&#xD;&#xA;（五）其他导致夫妻感情破裂的情形。&#xD;&#xA;《最高人民法院关于适用&lt;中华人民共和国民事诉讼法&gt;的解释》&#xD;&#xA;第九十条  当事人对自己提出的诉讼请求所依据的事实或者反驳对方诉讼请求所依据的事实，应当提供证据加以证明，但法律另有规定的除外。&#xD;&#xA;在作出判决前，当事人未能提供证据或者证据不足以证明其事实主张的，由负有举证证明责任的当事人承担不利的后果。&#xD;&#xA;1&#xD;&#xA;4&#xD;&#xA;3&#xD;" nameCN="全文">
  <WS value="天津市宝坻区人民法院 民事判决书 （2015）宝民初字第4723号" nameCN="文首">
    <WSZZDW value="法院" nameCN="文书制作单位" />
    <JBFY value="天津市宝坻区人民法院" nameCN="经办法院">
      <FYJB value="基层" nameCN="法院级别" />
      <XZQH_P value="天津" nameCN="行政区划(省)" />
    </JBFY>
    <WSMC value="民事判决书" nameCN="文书名称" />
    <AH value="（2015）宝民初字第4723号" nameCN="案号" />
    <LAND value="2015" nameCN="立案年度" />
    <AJXZ value="民事案件" nameCN="案件性质" />
    <WSZL value="判决书" nameCN="文书种类" />
    <SPCX value="一审案件" nameCN="审判程序" />
    <AJLX value="民事一审案件" nameCN="案件类型" />
  </WS>
  <SSCYRQJ value="原告蒋自秀，女，1972年5月27日出生（公民身份号码120224197205275923），汉族，农民，户籍住所天津市宝坻区八门城镇欢喜庄村9排20号，现住天津市宝坻区宝平街道西南楼宿舍24栋164号。 被告刘顺东，男，1971年4月6日出生（公民身份号码120224197104065919），汉族，农民，户籍住所天津市宝坻区八门城镇欢喜庄村9排20号，现住天津市宝坻区宝平街道西南楼宿舍24栋164号。" nameCN="诉讼参与人全集">
    <SSCYR value="原告蒋自秀，女，1972年5月27日出生（公民身份号码120224197205275923），汉族，农民，户籍住所天津市宝坻区八门城镇欢喜庄村9排20号，现住天津市宝坻区宝平街道西南楼宿舍24栋164号。" nameCN="诉讼参与人">
      <SSCYRMC value="蒋自秀" nameCN="诉讼参与人名称" />
      <SSSF value="原告" nameCN="诉讼身份" />
      <SSDW value="原告" nameCN="诉讼地位" />
      <DSRLB value="原告" nameCN="当事人类别" />
      <DSRLX value="自然人" nameCN="当事人类型" />
      <XB value="女" nameCN="性别" />
      <MZ value="汉族" nameCN="民族" />
      <CSRQ value="1972年5月27日" nameCN="出生日期">
        <Year value="1972" nameCN="年" />
        <Month value="5" nameCN="月" />
        <Day value="27" nameCN="日" />
      </CSRQ>
      <GJ value="中国" nameCN="国籍" />
      <DSRDZ value="天津市宝坻区宝平街道西南楼宿舍24栋164号" nameCN="当事人地址" />
      <DTQK value="到庭" nameCN="到庭情况" />
      <DWZWFZ nameCN="单位职务分组">
        <ZW value="农民" nameCN="职务" />
      </DWZWFZ>
      <DSRSFZH value="否" nameCN="当事人是否再婚" />
    </SSCYR>
    <SSCYR value="被告刘顺东，男，1971年4月6日出生（公民身份号码120224197104065919），汉族，农民，户籍住所天津市宝坻区八门城镇欢喜庄村9排20号，现住天津市宝坻区宝平街道西南楼宿舍24栋164号。" nameCN="诉讼参与人">
      <SSCYRMC value="刘顺东" nameCN="诉讼参与人名称" />
      <SSSF value="被告" nameCN="诉讼身份" />
      <SSDW value="被告" nameCN="诉讼地位" />
      <DSRLB value="被告" nameCN="当事人类别" />
      <DSRLX value="自然人" nameCN="当事人类型" />
      <XB value="男" nameCN="性别" />
      <MZ value="汉族" nameCN="民族" />
      <CSRQ value="1971年4月6日" nameCN="出生日期">
        <Year value="1971" nameCN="年" />
        <Month value="4" nameCN="月" />
        <Day value="6" nameCN="日" />
      </CSRQ>
      <GJ value="中国" nameCN="国籍" />
      <DSRDZ value="天津市宝坻区宝平街道西南楼宿舍24栋164号" nameCN="当事人地址" />
      <DTQK value="到庭" nameCN="到庭情况" />
      <DWZWFZ nameCN="单位职务分组">
        <ZW value="农民" nameCN="职务" />
      </DWZWFZ>
      <DSRSFZH value="否" nameCN="当事人是否再婚" />
    </SSCYR>
    <SSCYRQJ value="错误" nameCN="保险公司是否作为被告" />
  </SSCYRQJ>
  <SSJL value="原告蒋自秀与被告刘顺东离婚纠纷一案，本院于2015年5月29日立案受理后，依法由审判员郝志军独任审判，公开开庭进行了审理。原告蒋自秀、被告刘顺东到庭参加诉讼。本案现已审理终结。" nameCN="诉讼记录">
    <AY value="离婚纠纷" nameCN="案由" />
    <KTSL value="是" nameCN="开庭审理" />
    <KTSLXX value="公开审理" nameCN="开庭审理信息" />
    <WZAY value="离婚纠纷" nameCN="完整案由" />
    <AYDM value="9015" nameCN="案由代码" />
    <LARQ value="2015年5月29日" nameCN="立案日期" />
    <YSAJSYCX value="普通程序" nameCN="一审案件适用程序" />
    <JYZPT value="否" nameCN="简易转普通" />
    <YSAJLY value="新收" nameCN="一审案件来源" />
    <SLRQ value="2015年5月29日" nameCN="受理日期" />
    <CTDSRXX nameCN="出庭当事人信息">
      <CTRXM value="刘顺东" nameCN="出庭人姓名">
        <SSDW value="被告" nameCN="诉讼地位" />
      </CTRXM>
      <CTRXM value="蒋自秀" nameCN="出庭人姓名">
        <SSDW value="原告" nameCN="诉讼地位" />
      </CTRXM>
    </CTDSRXX>
  </SSJL>
  <AJJBQK value="原告诉称，原、被告于1993年秋经人介绍相识并确立恋爱关系，1994年4月6日登记结婚开始共同生活。1995年2月9生育长女刘怡，现在天津农学院读书。2003年6月25日生育长子刘鑫杨，现在宝坻区第八小学读书。被告性格固执且脾气暴躁，动辄找茬与原告打架。因感情不合原告曾在1998年提出过离婚诉讼，因被告不同意离婚被驳回了离婚的请求。原告考虑到孩子尚小，为了给孩子一个完整的家，一直忍辱负重勉强与被告生活在一起，但被告根本不知道理解原告，依然我行我素、酗酒成性，还生性多疑对原告无端怀疑直至大打出手，经常对原告施以家庭暴力。现双方没有任何感情可言，为尽早解除这段痛苦的婚姻，原告提起诉讼请求：1、依法判准原、被告离婚。2、判令原、被告之子刘鑫杨随原告生活，被告每月给付抚养费800元至其独立生活时止；原、被告之女刘怡随原告生活，被告每月给付教育费、生活费3000元。3、夫妻共同财产宝坻区八门城镇欢喜庄村村西自建门脸房价值80000元，宝坻区八门城镇欢喜庄村9排20号住宅建院墙、厢房价值30000元，夏利牌轿车1辆价值5000元，新型802DB—2推土机1台价值80000元，五羊牌摩托车1辆价值2000元，手扶拖拉机1辆价值2000元归被告所有，被告给付原告折价款100000元。4、诉讼费用由被告承担。 原告为支持其主张提交如下证据：原、被告结婚证复印件1份；原、被告及原、被告之女刘怡、之子刘鑫杨户口页复印件各1份；申请法院调取原告在公安宝坻分局宝平派出所询问笔录及诊断证明书，证明被告殴打原告的情况。 被告辩称，1998年与原告闹离婚，不是因为感情不和，是因为被告的父母。这次打架责任在被告，是被告喝酒动手打了原告，对原告的伤害也挺大，在此向原告道歉，请求原告的原谅并保证以后再不喝酒了，毕竟与原告有二十多年的夫妻感情，所以不同意离婚。 被告未提交证据。 经审理查明，原、被告于1993年秋经人介绍相识并确立恋爱关系，1994年4月6日登记结婚开始共同生活。1995年2月9生育长女刘怡，现在天津农学院读书。2003年6月25日生育长子刘鑫杨，现在宝坻区第八小学读书。2015年5月25日，原、被告因家庭琐事发生争吵、打架。5月29日后双方开始分居至今。 庭审中，被告承认5月25日那天酒后与原告发生厮打，亦承认都是被告的错。" nameCN="案件基本情况">
    <YGSCD value="原告诉称，原、被告于1993年秋经人介绍相识并确立恋爱关系，1994年4月6日登记结婚开始共同生活。1995年2月9生育长女刘怡，现在天津农学院读书。2003年6月25日生育长子刘鑫杨，现在宝坻区第八小学读书。被告性格固执且脾气暴躁，动辄找茬与原告打架。因感情不合原告曾在1998年提出过离婚诉讼，因被告不同意离婚被驳回了离婚的请求。原告考虑到孩子尚小，为了给孩子一个完整的家，一直忍辱负重勉强与被告生活在一起，但被告根本不知道理解原告，依然我行我素、酗酒成性，还生性多疑对原告无端怀疑直至大打出手，经常对原告施以家庭暴力。现双方没有任何感情可言，为尽早解除这段痛苦的婚姻，原告提起诉讼请求：1、依法判准原、被告离婚。2、判令原、被告之子刘鑫杨随原告生活，被告每月给付抚养费800元至其独立生活时止；原、被告之女刘怡随原告生活，被告每月给付教育费、生活费3000元。3、夫妻共同财产宝坻区八门城镇欢喜庄村村西自建门脸房价值80000元，宝坻区八门城镇欢喜庄村9排20号住宅建院墙、厢房价值30000元，夏利牌轿车1辆价值5000元，新型802DB—2推土机1台价值80000元，五羊牌摩托车1辆价值2000元，手扶拖拉机1辆价值2000元归被告所有，被告给付原告折价款100000元。4、诉讼费用由被告承担。 " nameCN="原告诉称段">
      <SSJE nameCN="交通事故原告诉称诉讼金额">
        <SSJESL value="800元" nameCN="金额">
          <SSJELX value="抚养费" nameCN="类型" />
        </SSJESL>
        <SSJESL value="3000元" nameCN="金额">
          <SSJELX value="生活费" nameCN="类型" />
        </SSJESL>
        <SSJESL value="80000元" nameCN="金额" />
        <SSJESL value="30000元" nameCN="金额" />
        <SSJESL value="5000元" nameCN="金额" />
        <SSJESL value="80000元" nameCN="金额" />
        <SSJESL value="2000元" nameCN="金额" />
        <SSJESL value="2000元" nameCN="金额" />
        <SSJESL value="100000元" nameCN="金额">
          <SSJELX value="价款" nameCN="类型" />
          <SSJELX value="折价款" nameCN="类型" />
        </SSJESL>
      </SSJE>
    </YGSCD>
    <SGXQ value="未提及" nameCN="事故详情">
      <SGSJ value="未提及" nameCN="事故时间" />
      <SGDD value="未提及" nameCN="事故地点" />
    </SGXQ>
    <JDCSYR value="刘顺东" nameCN="机动车所有人" />
    <SHRJZD value="天津市宝坻区宝平街道西南楼宿舍24栋164号" nameCN="受害人居住地" />
    <SHRZY value="农民" nameCN="受害人职业" />
    <BGBCD value="被告辩称，1998年与原告闹离婚，不是因为感情不和，是因为被告的父母。这次打架责任在被告，是被告喝酒动手打了原告，对原告的伤害也挺大，在此向原告道歉，请求原告的原谅并保证以后再不喝酒了，毕竟与原告有二十多年的夫妻感情，所以不同意离婚。 " nameCN="被告辩称段" />
    <ZJD value="原告为支持其主张提交如下证据：原、被告结婚证复印件1份；原、被告及原、被告之女刘怡、之子刘鑫杨户口页复印件各1份；申请法院调取原告在公安宝坻分局宝平派出所询问笔录及诊断证明书，证明被告殴打原告的情况。" nameCN="证据段" />
    <ZJD value="被告未提交证据。 " nameCN="证据段" />
    <CMSSD value="经审理查明，原、被告于1993年秋经人介绍相识并确立恋爱关系，1994年4月6日登记结婚开始共同生活。1995年2月9生育长女刘怡，现在天津农学院读书。2003年6月25日生育长子刘鑫杨，现在宝坻区第八小学读书。2015年5月25日，原、被告因家庭琐事发生争吵、打架。5月29日后双方开始分居至今。庭审中，被告承认5月25日那天酒后与原告发生厮打，亦承认都是被告的错。 " nameCN="查明事实段" />
  </AJJBQK>
  <CPFXGC value="本院认为，夫妻之间应互相尊重，互谅互让，和睦相处，为子女创建温馨和谐的家庭环境。原、被告结婚二十多年，并生育一女一子，应有较深的感情基础。在共同生活期间因琐事发生争吵，产生矛盾是很难避免的，但被告动手殴打原告是不对的，在此对被告提出批评。此案经调解原告坚持离婚，被告不同意离婚，但原告提交的证据不足以证明双方感情已彻底破裂，故对原告的请求本院不予支持。希望双方在今后的共同生活中，加强沟通，勤于交流，彼此信任，珍惜夫妻感情，以有利于子女的健康成长。依据《中华人民共和国婚姻法》第三十二条第二款，《最高人民法院关于适用&lt;中华人民共和国民事诉讼法&gt;的解释》第九十条之规定，判决如下：" nameCN="裁判分析过程">
    <JAFSLX value="判决" nameCN="结案方式类型" />
    <FLFTMC value="中华人民共和国婚姻法" nameCN="法律法条名称">
      <TM value="三十二" nameCN="条目">
        <KM value="第二款" nameCN="款目" />
      </TM>
    </FLFTMC>
    <FLFTMC value="最高人民法院关于适用&lt;中华人民共和国民事诉讼法&gt;的解释" nameCN="法律法条名称">
      <TM value="九十" nameCN="条目" />
    </FLFTMC>
  </CPFXGC>
  <CPJG value="驳回原告蒋自秀离婚的诉讼请求。 案件受理费214元，已减半收取107元（该款原告已交纳），由原告蒋自秀负担100元，其余7元退回原告蒋自秀。 如不服本判决，可在判决书送达之日起十五日内，向本院递交上诉状，并按对方当事人的人数提出副本，上诉于天津市第一中级人民法院。" nameCN="裁判结果">
    <JAFS value="判决" nameCN="结案方式" />
    <PCSFSXZQ value="正确" nameCN="同时起诉侵权人与保险公司的赔偿顺序" />
    <JTPJJG value="驳回原告蒋自秀离婚的诉讼请求。" nameCN="具体裁判段" />
    <SSFCD nameCN="诉讼费承担">
      <SSFCDJL value="案件受理费214元，已减半收取107元（该款原告已交纳），由原告蒋自秀负担100元，其余7元退回原告蒋自秀。" nameCN="诉讼费承担记录">
        <SSFJE value="107元" nameCN="诉讼费金额" />
        <SSFZL value="受理费" nameCN="诉讼费种类" />
        <SSFCDR value="蒋自秀" nameCN="承担人">
          <SSFCDJE value="100元" nameCN="承担金额" />
          <SSFCDFS value="个人独立承担该金额" nameCN="承担方式" />
          <SSFCDDW value="原告" nameCN="承担人地位" />
        </SSFCDR>
      </SSFCDJL>
    </SSFCD>
    <SFFHCS value="否" nameCN="是否发回重审" />
    <KSSZ value="天津市第一中级人民法院" nameCN="可上诉至" />
    <SSTJCL value="上诉状，并按对方当事人的人数提出副本" nameCN="上诉提交材料" />
    <SSQX value="十五日" nameCN="上诉期限" />
    <TCGXQYY value="否" nameCN="是否提出管辖权异议" />
  </CPJG>
  <WW value="审判员郝志军 二○一五年六月二十三日 书记员杜建玥" nameCN="文尾">
    <SPZZCY nameCN="审判组织成员">
      <SPRYXM value="杜建玥" nameCN="审判人员姓名" />
      <SPRYJS value="书记员" nameCN="审判人员角色" />
    </SPZZCY>
    <SPZZCY nameCN="审判组织成员">
      <SPRYXM value="郝志军" nameCN="审判人员姓名" />
      <SPRYJS value="审判员" nameCN="审判人员角色" />
    </SPZZCY>
    <CPSJ value="2015年6月23日" nameCN="裁判时间">
      <Year value="2015" nameCN="结案年度" />
      <JANYR value="2015年6月23日" nameCN="结案年月日" />
      <JANY value="2015-6" nameCN="结案年月" />
      <Month value="6" nameCN="月" />
      <Day value="23" nameCN="日" />
    </CPSJ>
  </WW>
</QW>

