<?xml version="1.0" encoding="UTF-8"?>
<QW value="天津市宝坻区人民法院&#xD;&#xA;民事判决书&#xD;&#xA;（2012）宝民初字第4514号&#xD;&#xA;原告李金凤，女，1960年2月1日出生，汉族，居民，住天津市宝坻区海滨街道大吴路3条2号。&#xD;&#xA;被告韩明，男，1953年2月11日出生，汉族，宝坻区邮政储蓄银行职工，住天津市宝坻区宝平街道建设楼11-6-501室。&#xD;&#xA;原告李金凤与被告韩明离婚纠纷一案，本院于2012年7月23日立案受理后，依法由代理审判员何玉江独任审判并公开开庭进行了审理。原、被告到庭参加诉讼，本案现已审理终结。&#xD;&#xA;原告诉称， 2006年2月，原、被告经婚介所介绍相识后确立恋爱关系，2006年5月10日登记结婚并共同生活（原、被告均系再婚）。因婚前缺乏了解，草率结婚，未建立起牢固的夫妻感情。婚后双方因生活琐事经常争吵，无法像正常夫妻经常聊天沟通，被告常因一点小事同原告矫情个没完没了，原告百般努力也无法改变现状。近年来，原告每次听到被告絮叨就失眠，夫妻感情已经破裂，故起诉要求：一、判令原告与被告离婚；二、诉讼费用由被告承担。&#xD;&#xA;被告辩称，原告于2012年6月27日离家至今未归，被告发很多短信让她回家，但原告拒绝回家，故被告同意离婚。但是双方结婚7年，被告付出很多，原告要求离婚，被告家庭没有了，另外原告新买了楼房，写的是原告之女屈荣霞的名字，故要求原告给付被告经济赔偿款20万元及楼房折价款10万元。&#xD;&#xA;经审理查明，原、被告均系再婚。双方于2006年2月经婚姻介绍所介绍相识后确立恋爱关系，2006年5月10日登记结婚共同生活。双方婚后因生活琐事发生矛盾，2012年6月27日分居至今。此案经本院主持调解，双方均同意离婚。&#xD;&#xA;庭审中，被告主张结婚7年，付出很多，因原告要求离婚致使被告没了家庭，故要求原告给付经济赔偿20万元。另2012年原告以其女儿屈荣霞的名义购买了华苑东区25-4-501室房屋1所，要求原告给付楼房折价款10万元。经查，原告之女屈荣霞于2012年4月6日结婚，华苑东区25-4-501室权利登记人为原告之女屈荣霞，购买于2012年6月。&#xD;&#xA;另查，双方无共同财产、债权、债务。&#xD;&#xA;本院认为，原、被告认识时间较短即草率结婚，婚后因生活琐事发生矛盾后分居生活，庭审中，双方均同意离婚，说明夫妻感情确已破裂，故应准予双方离婚。被告要求原告给付经济赔偿款20万元无事实及法律依据，本院不予支持。被告主张原告以其女屈荣霞的名义购买了楼房，要求原告给付楼房折价款10万元，未提供相应证据予以证明，且该楼房系屈荣霞婚后购买，故本院对被告上述抗辩意见不予采信。此案经调解未果，故依照《中华人民共和国婚姻法》第三十二条第二款、《中华人民共和国民事诉讼法》第六十四条第一款、最高人民法院《关于民事诉讼证据的若干规定》第二条之规定，判决如下：&#xD;&#xA;准予原告李金凤与被告韩明离婚。&#xD;&#xA;诉讼费用100元（原告已预交）由被告承担，于判决生效后立即交纳。&#xD;&#xA;如不服本判决，可在判决书送达之日起十五日内，向本院递交上诉状，并按对方当事人的人数提出副本，上诉于天津市第一中级人民法院。&#xD;&#xA;代理审判员    何玉江&#xD;&#xA;二○一二年八月  日&#xD;&#xA;书  记  员    王晶晶&#xD;&#xA;附相关法律条款：&#xD;&#xA;《中华人民共和国婚姻法》第三十二条第二款：人民法院审理离婚案件，应当进行调解；如感情确已破裂，调解无效，应准予离婚。&#xD;&#xA;《中华人民共和国民事诉讼法》第六十四条第一款：当事人对自己提出的主张，有责任提供证据。&#xD;&#xA;最高人民法院《关于民事诉讼证据的若干规定》第二条:当事人对自己提出的诉讼请求所依据的事实或者反驳对方诉讼请求所依据的事实有责任提供证据加以证明。没有证据或者证据不足以证明当事人的事实主张的，有负有举证责任的当事人承担不利后果。&#xD;&#xA;1&#xD;&#xA;2&#xD;&#xA;3&#xD;" nameCN="全文">
  <WS value="天津市宝坻区人民法院 民事判决书 （2012）宝民初字第4514号" nameCN="文首">
    <WSZZDW value="法院" nameCN="文书制作单位" />
    <JBFY value="天津市宝坻区人民法院" nameCN="经办法院">
      <FYJB value="基层" nameCN="法院级别" />
      <XZQH_P value="天津" nameCN="行政区划(省)" />
    </JBFY>
    <WSMC value="民事判决书" nameCN="文书名称" />
    <AH value="（2012）宝民初字第4514号" nameCN="案号" />
    <LAND value="2012" nameCN="立案年度" />
    <AJXZ value="民事案件" nameCN="案件性质" />
    <WSZL value="判决书" nameCN="文书种类" />
    <SPCX value="一审案件" nameCN="审判程序" />
    <AJLX value="民事一审案件" nameCN="案件类型" />
  </WS>
  <SSCYRQJ value="原告李金凤，女，1960年2月1日出生，汉族，居民，住天津市宝坻区海滨街道大吴路3条2号。 被告韩明，男，1953年2月11日出生，汉族，宝坻区邮政储蓄银行职工，住天津市宝坻区宝平街道建设楼11-6-501室。" nameCN="诉讼参与人全集">
    <SSCYR value="原告李金凤，女，1960年2月1日出生，汉族，居民，住天津市宝坻区海滨街道大吴路3条2号。" nameCN="诉讼参与人">
      <SSCYRMC value="李金凤" nameCN="诉讼参与人名称" />
      <SSSF value="原告" nameCN="诉讼身份" />
      <SSDW value="原告" nameCN="诉讼地位" />
      <DSRLB value="原告" nameCN="当事人类别" />
      <DSRLX value="自然人" nameCN="当事人类型" />
      <XB value="女" nameCN="性别" />
      <MZ value="汉族" nameCN="民族" />
      <CSRQ value="1960年2月1日" nameCN="出生日期">
        <Year value="1960" nameCN="年" />
        <Month value="2" nameCN="月" />
        <Day value="1" nameCN="日" />
      </CSRQ>
      <GJ value="中国" nameCN="国籍" />
      <DSRDZ value="天津市宝坻区海滨街道大吴路3条2号" nameCN="当事人地址" />
      <DSRSFZH value="是" nameCN="当事人是否再婚" />
    </SSCYR>
    <SSCYR value="被告韩明，男，1953年2月11日出生，汉族，宝坻区邮政储蓄银行职工，住天津市宝坻区宝平街道建设楼11-6-501室。" nameCN="诉讼参与人">
      <SSCYRMC value="韩明" nameCN="诉讼参与人名称" />
      <SSSF value="被告" nameCN="诉讼身份" />
      <SSDW value="被告" nameCN="诉讼地位" />
      <DSRLB value="被告" nameCN="当事人类别" />
      <DSRLX value="自然人" nameCN="当事人类型" />
      <XB value="男" nameCN="性别" />
      <MZ value="汉族" nameCN="民族" />
      <CSRQ value="1953年2月11日" nameCN="出生日期">
        <Year value="1953" nameCN="年" />
        <Month value="2" nameCN="月" />
        <Day value="11" nameCN="日" />
      </CSRQ>
      <GJ value="中国" nameCN="国籍" />
      <DSRDZ value="天津市宝坻区宝平街道建设楼11-6-501室" nameCN="当事人地址" />
      <DWZWFZ nameCN="单位职务分组">
        <ZW value="职工" nameCN="职务" />
      </DWZWFZ>
      <DSRSFZH value="是" nameCN="当事人是否再婚" />
    </SSCYR>
    <SSCYRQJ value="错误" nameCN="保险公司是否作为被告" />
  </SSCYRQJ>
  <SSJL value="原告李金凤与被告韩明离婚纠纷一案，本院于2012年7月23日立案受理后，依法由代理审判员何玉江独任审判并公开开庭进行了审理。原、被告到庭参加诉讼，本案现已审理终结。" nameCN="诉讼记录">
    <AY value="离婚纠纷" nameCN="案由" />
    <KTSL value="是" nameCN="开庭审理" />
    <KTSLXX value="公开审理" nameCN="开庭审理信息" />
    <WZAY value="离婚纠纷" nameCN="完整案由" />
    <AYDM value="9015" nameCN="案由代码" />
    <LARQ value="2012年7月23日" nameCN="立案日期" />
    <YSAJSYCX value="普通程序" nameCN="一审案件适用程序" />
    <JYZPT value="否" nameCN="简易转普通" />
    <YSAJLY value="新收" nameCN="一审案件来源" />
    <SLRQ value="2012年7月23日" nameCN="受理日期" />
  </SSJL>
  <AJJBQK value="原告诉称，2006年2月，原、被告经婚介所介绍相识后确立恋爱关系，2006年5月10日登记结婚并共同生活（原、被告均系再婚）。因婚前缺乏了解，草率结婚，未建立起牢固的夫妻感情。婚后双方因生活琐事经常争吵，无法像正常夫妻经常聊天沟通，被告常因一点小事同原告矫情个没完没了，原告百般努力也无法改变现状。近年来，原告每次听到被告絮叨就失眠，夫妻感情已经破裂，故起诉要求：一、判令原告与被告离婚；二、诉讼费用由被告承担。 被告辩称，原告于2012年6月27日离家至今未归，被告发很多短信让她回家，但原告拒绝回家，故被告同意离婚。但是双方结婚7年，被告付出很多，原告要求离婚，被告家庭没有了，另外原告新买了楼房，写的是原告之女屈荣霞的名字，故要求原告给付被告经济赔偿款20万元及楼房折价款10万元。 经审理查明，原、被告均系再婚。双方于2006年2月经婚姻介绍所介绍相识后确立恋爱关系，2006年5月10日登记结婚共同生活。双方婚后因生活琐事发生矛盾，2012年6月27日分居至今。此案经本院主持调解，双方均同意离婚。 庭审中，被告主张结婚7年，付出很多，因原告要求离婚致使被告没了家庭，故要求原告给付经济赔偿20万元。另2012年原告以其女儿屈荣霞的名义购买了华苑东区25-4-501室房屋1所，要求原告给付楼房折价款10万元。经查，原告之女屈荣霞于2012年4月6日结婚，华苑东区25-4-501室权利登记人为原告之女屈荣霞，购买于2012年6月。 另查，双方无共同财产、债权、债务。" nameCN="案件基本情况">
    <YGSCD value="原告诉称，2006年2月，原、被告经婚介所介绍相识后确立恋爱关系，2006年5月10日登记结婚并共同生活（原、被告均系再婚）。因婚前缺乏了解，草率结婚，未建立起牢固的夫妻感情。婚后双方因生活琐事经常争吵，无法像正常夫妻经常聊天沟通，被告常因一点小事同原告矫情个没完没了，原告百般努力也无法改变现状。近年来，原告每次听到被告絮叨就失眠，夫妻感情已经破裂，故起诉要求：一、判令原告与被告离婚；二、诉讼费用由被告承担。 " nameCN="原告诉称段" />
    <SGXQ value="未提及" nameCN="事故详情">
      <SGSJ value="未提及" nameCN="事故时间" />
      <SGDD value="未提及" nameCN="事故地点" />
    </SGXQ>
    <JDCSYR value="韩明" nameCN="机动车所有人" />
    <SHRJZD value="天津市宝坻区海滨街道大吴路3条2号" nameCN="受害人居住地" />
    <BGBCD value="被告辩称，原告于2012年6月27日离家至今未归，被告发很多短信让她回家，但原告拒绝回家，故被告同意离婚。但是双方结婚7年，被告付出很多，原告要求离婚，被告家庭没有了，另外原告新买了楼房，写的是原告之女屈荣霞的名字，故要求原告给付被告经济赔偿款20万元及楼房折价款10万元。 " nameCN="被告辩称段" />
    <CMSSD value="经审理查明，原、被告均系再婚。双方于2006年2月经婚姻介绍所介绍相识后确立恋爱关系，2006年5月10日登记结婚共同生活。双方婚后因生活琐事发生矛盾，2012年6月27日分居至今。此案经本院主持调解，双方均同意离婚。庭审中，被告主张结婚7年，付出很多，因原告要求离婚致使被告没了家庭，故要求原告给付经济赔偿20万元。另2012年原告以其女儿屈荣霞的名义购买了华苑东区25-4-501室房屋1所，要求原告给付楼房折价款10万元。经查，原告之女屈荣霞于2012年4月6日结婚，华苑东区25-4-501室权利登记人为原告之女屈荣霞，购买于2012年6月。 另查，双方无共同财产、债权、债务。 " nameCN="查明事实段" />
  </AJJBQK>
  <CPFXGC value="本院认为，原、被告认识时间较短即草率结婚，婚后因生活琐事发生矛盾后分居生活，庭审中，双方均同意离婚，说明夫妻感情确已破裂，故应准予双方离婚。被告要求原告给付经济赔偿款20万元无事实及法律依据，本院不予支持。被告主张原告以其女屈荣霞的名义购买了楼房，要求原告给付楼房折价款10万元，未提供相应证据予以证明，且该楼房系屈荣霞婚后购买，故本院对被告上述抗辩意见不予采信。此案经调解未果，故依照《中华人民共和国婚姻法》第三十二条第二款、《中华人民共和国民事诉讼法》第六十四条第一款、最高人民法院《关于民事诉讼证据的若干规定》第二条之规定，判决如下：" nameCN="裁判分析过程">
    <JAFSLX value="判决" nameCN="结案方式类型" />
    <FLFTMC value="中华人民共和国婚姻法" nameCN="法律法条名称">
      <TM value="三十二" nameCN="条目">
        <KM value="第二款" nameCN="款目" />
      </TM>
    </FLFTMC>
    <FLFTMC value="中华人民共和国民事诉讼法" nameCN="法律法条名称">
      <TM value="六十四" nameCN="条目">
        <KM value="第一款" nameCN="款目" />
      </TM>
    </FLFTMC>
    <FLFTMC value="关于民事诉讼证据的若干规定" nameCN="法律法条名称">
      <TM value="二" nameCN="条目" />
    </FLFTMC>
  </CPFXGC>
  <CPJG value="准予原告李金凤与被告韩明离婚。 诉讼费用100元（原告已预交）由被告承担，于判决生效后立即交纳。 如不服本判决，可在判决书送达之日起十五日内，向本院递交上诉状，并按对方当事人的人数提出副本，上诉于天津市第一中级人民法院。" nameCN="裁判结果">
    <JAFS value="判决" nameCN="结案方式" />
    <PCSFSXZQ value="正确" nameCN="同时起诉侵权人与保险公司的赔偿顺序" />
    <JTPJJG value="准予原告李金凤与被告韩明离婚。" nameCN="具体裁判段" />
    <SSFCD nameCN="诉讼费承担">
      <SSFCDJL value="诉讼费用100元（原告已预交）由被告承担，于判决生效后立即交纳。" nameCN="诉讼费承担记录">
        <SSFJE value="100元" nameCN="诉讼费金额" />
        <SSFZL value="诉讼费用" nameCN="诉讼费种类" />
      </SSFCDJL>
    </SSFCD>
    <SFFHCS value="否" nameCN="是否发回重审" />
    <KSSZ value="天津市第一中级人民法院" nameCN="可上诉至" />
    <SSTJCL value="上诉状，并按对方当事人的人数提出副本" nameCN="上诉提交材料" />
    <SSQX value="十五日" nameCN="上诉期限" />
    <TCGXQYY value="否" nameCN="是否提出管辖权异议" />
  </CPJG>
  <WW value="代理审判员何玉江 二○一二年八月日 书记员王晶晶" nameCN="文尾">
    <SPZZCY nameCN="审判组织成员">
      <SPRYXM value="何玉江" nameCN="审判人员姓名" />
      <SPRYJS value="代理审判员" nameCN="审判人员角色" />
    </SPZZCY>
    <SPZZCY nameCN="审判组织成员">
      <SPRYXM value="王晶晶" nameCN="审判人员姓名" />
      <SPRYJS value="书记员" nameCN="审判人员角色" />
    </SPZZCY>
  </WW>
</QW>

